Workbook
Name UPDATE: 'Data Sheet'!$E$1

Sheet Data Sheet
A1: COMPANY NAME | B1: TVS MOTOR COMPANY LTD | E1: =IF(B2<>B3, "A NEW VERSION OF THE WORKSHEET IS AVAILABLE", "")
A2: LATEST VERSION | B2: 2.1 | E2: PLEASE DO NOT MAKE ANY CHANGES TO THIS SHEET
A3: CURRENT VERSION | B3: 2.1
A5: META
A6: Number of shares | B6: =IF(B9>0, B9/B8, 0) -> 47.469797
A7: Face Value | B7: 1
A8: Current Price | B8: 4313.1
A9: Market Capitalization | B9: 204741.98
A15: PROFIT & LOSS
A16: Report Date | B16: 42825 | C16: 43190 | D16: 43555 | E16: 43921 | F16: 44286 | G16: 44651 | H16: 45016 | I16: 45382 | J16: 45747 | K16: 46112
A17: Sales | B17: 12462.62 | C17: 16340.25 | D17: 20159.99 | E17: 18849.31 | F17: 19420.82 | G17: 24355.31 | H17: 31973.99 | I17: 38778.82 | J17: 44089.01 | K17: 56069.52
A18: Raw Material Cost | B18: 8985.23 | C18: 11257.6 | D18: 14033.27 | E18: 12310.04 | F18: 12925.65 | G18: 16517.69 | H18: 20987.19 | I18: 24593.59 | J18: 26803.06 | K18: 34500.71
A19: Change in Inventory | B19: 48.77 | C19: -33.96 | D19: 78.95 | E19: -6.73 | F19: 0.19 | G19: 260.4 | H19: 140.93 | I19: 323.37 | J19: 79.22 | K19: -379.05
A20: Power and Fuel | B20: 108.83 | C20: 128.63 | D20: 136.59 | E20: 112.75 | F20: 96.14 | G20: 126.81 | H20: 133.47 | I20: 104.53 | J20: 118.63 | K20: 141.84
A21: Other Mfr. Exp | B21: 142.71 | C21: 156.57 | D21: 155.03 | E21: 154.06 | F21: 142.23 | G21: 160.71 | H21: 209.5 | I21: 245.47 | J21: 334.37 | K21: 347.57
A22: Employee Cost | B22: 828.05 | C22: 1149.79 | D22: 1432.15 | E22: 1539.35 | F22: 1689.37 | G22: 2124.62 | H22: 2890.25 | I22: 3297.72 | J22: 3580.88 | K22: 4391.61
A23: Selling and admin | B23: 1137.29 | C23: 1370.71 | D23: 1208.18 | E23: 1223.87 | F23: 986.91 | G23: 1138.3 | H23: 1353.75 | I23: 1804.37 | J23: 2315.47 | K23: 2855.94
A24: Other Expenses | B24: 438.02 | C24: 671.51 | D24: 1110.68 | E24: 1238.05 | F24: 1348.67 | G24: 1792.95 | H24: 2514.11 | I24: 3621.96 | J24: 4428.22 | K24: 5100.53
A25: Other Income | B25: 163.14 | C25: 71.15 | D25: 24.92 | E25: 11.5 | F25: 35.9 | G25: -4.76 | H25: 136.13 | I25: 130.78 | J25: 86.47 | K25: -28.07
A26: Depreciation | B26: 316.82 | C26: 373.6 | D26: 441.71 | E26: 556 | F26: 564.82 | G26: 742.86 | H26: 858.86 | I26: 956.15 | J26: 1045.56 | K26: 1272.64
A27: Interest | B27: 59.62 | C27: 338.22 | D27: 663.4 | E27: 854.54 | F27: 881.49 | G27: 940.22 | H27: 1367.89 | I27: 1916.6 | J27: 2093.25 | K27: 2229.82
... A31: Dividend Amount | B31: 118.78 | C31: 156.78 | D31: 166.28 | E31: 166.28 | F31: 166.28 | G31: 178.16 | H31: 237.55 | I31: 380.08 | J31: 475.1 | K31: 570.12
A40: Quarters
A41: Report Date | B41: 45382 | C41: 45473 | D41: 45565 | E41: 45657 | F41: 45747 | G41: 45838 | H41: 45930 | I41: 46022 | J41: 46112 | K41: 46203
A42: Sales | B42: 9942.48 | C42: 10314.47 | D42: 11301.68 | E42: 11034.88 | F42: 11542 | G42: 12210.05 | H42: 14051.22 | I42: 14755.52 | J42: 15052.73 | K42: 16295.52
A43: Expenses | B43: 8487.4 | C43: 8883.6 | D43: 9678.14 | E43: 9401.91 | F43: 9638.36 | G43: 10407.13 | H43: 11941.12 | I43: 12488.11 | J43: 12880.89 | K43: 13952.36
A44: Other Income | B44: -33.87 | C44: 48.32 | D44: 32.31 | E44: 69.61 | F44: -57.35 | G44: 39.66 | H44: -14 | I44: -60.38 | J44: 6.65 | K44: 158.2
A45: Depreciation | B45: 263.38 | C45: 241.34 | D45: 259.29 | E45: 258.43 | F45: 291.8 | G45: 314.83 | H45: 320.42 | I45: 322.85 | J45: 314.54 | K45: 354
A46: Interest | B46: 510.82 | C46: 499.87 | D46: 509.04 | E46: 536.09 | F46: 550.8 | G46: 550.56 | H46: 552.39 | I46: 561.05 | J46: 565.82 | K46: 602.17
A47: Profit before tax | B47: 647.01 | C47: 737.98 | D47: 887.52 | E47: 908.06 | F47: 1003.69 | G47: 977.19 | H47: 1223.29 | I47: 1323.13 | J47: 1298.13 | K47: 1545.19
A48: Tax | B48: 235.48 | C48: 253.16 | D48: 299.39 | E48: 298.71 | F48: 306.18 | G48: 334.33 | H48: 390.53 | I48: 431.87 | J48: 478.58 | K48: 487.58
A49: Net profit | B49: 386.98 | C49: 460.88 | D49: 560.49 | E49: 566.03 | F49: 648.16 | G49: 610.04 | H49: 795.48 | I49: 841.29 | J49: 771.52 | K49: 1019.43
A50: Operating Profit | B50: 1455.08 | C50: 1430.87 | D50: 1623.54 | E50: 1632.97 | F50: 1903.64 | G50: 1802.92 | H50: 2110.1 | I50: 2267.41 | J50: 2171.84 | K50: 2343.16
A55: BALANCE SHEET
A56: Report Date | B56: 42825 | C56: 43190 | D56: 43555 | E56: 43921 | F56: 44286 | G56: 44651 | H56: 45016 | I56: 45382 | J56: 45747 | K56: 46112
A57: Equity Share Capital | B57: 47.51 | C57: 47.51 | D57: 47.51 | E57: 47.51 | F57: 47.51 | G57: 47.51 | H57: 47.51 | I57: 47.51 | J57: 47.51 | K57: 47.51
A58: Reserves | B58: 2168.53 | C58: 2629.69 | D58: 3122.66 | E58: 3234.59 | F58: 3779.1 | G58: 4351.94 | H58: 5457.49 | I58: 6736 | J58: 8455.87 | K58: 9516.74
A59: Borrowings | B59: 1310.8 | C59: 6927.54 | D59: 9298.05 | E59: 11591.45 | F59: 12179.16 | G59: 15827.21 | H59: 22375.58 | I59: 26005.7 | J59: 28608.71 | K59: 32791.01
A60: Other Liabilities | B60: 2601.12 | C60: 3585.56 | D60: 4228.27 | E60: 4398.62 | F60: 5859.3 | G60: 6692.44 | H60: 7143.96 | I60: 9234.79 | J60: 10538.8 | K60: 13790.36
A61: Total | B61: 6127.96 | C61: 13190.3 | D61: 16696.49 | E61: 19272.17 | F61: 21865.07 | G61: 26919.1 | H61: 35024.54 | I61: 42024 | J61: 47650.89 | K61: 56145.62
A62: Net Block | B62: 2362.06 | C62: 3093.85 | D62: 3366.8 | E62: 3810.69 | F62: 4221.05 | G62: 5974.64 | H62: 5748.03 | I62: 5890.82 | J62: 7644.45 | K62: 8633.95
A63: Capital Work in Progress | B63: 63.81 | C63: 313.26 | D63: 744.51 | E63: 1006.01 | F63: 1040.77 | G63: 551.53 | H63: 743.45 | I63: 1032.95 | J63: 1465.45 | K63: 2072.22
A64: Investments | B64: 1155.19 | C64: 421.02 | D64: 439.73 | E64: 370.91 | F64: 468.01 | G64: 604.56 | H64: 967.25 | I64: 1123.19 | J64: 1247.38 | K64: 1146.64
A65: Other Assets | B65: 2546.9 | C65: 9362.17 | D65: 12145.45 | E65: 14084.56 | F65: 16135.24 | G65: 19788.37 | H65: 27565.81 | I65: 33977.04 | J65: 37293.61 | K65: 44292.81
A66: Total | B66: 6127.96 | C66: 13190.3 | D66: 16696.49 | E66: 19272.17 | F66: 21865.07 | G66: 26919.1 | H66: 35024.54 | I66: 42024 | J66: 47650.89 | K66: 56145.62
A67: Receivables | B67: 701.81 | C67: 1070.88 | D67: 1546.07 | E67: 1454.36 | F67: 1029.26 | G67: 1177.3 | H67: 1256.42 | I67: 1839.42 | J67: 1716.75 | K67: 2654.13
... A70: No. of Equity Shares | B70: 475087114 | C70: 475087114 | D70: 475087114 | E70: 475087114 | F70: 475087114 | G70: 475087114 | H70: 475087114 | I70: 475087114 | J70: 475087114 | K70: 475087114
A71: New Bonus Shares
A72: Face value | B72: 1 | C72: 1 | D72: 1 | E72: 1 | F72: 1 | G72: 1 | H72: 1 | I72: 1 | J72: 1 | K72: 1
A80: CASH FLOW:
A81: Report Date | B81: 42825 | C81: 43190 | D81: 43555 | E81: 43921 | F81: 44286 | G81: 44651 | H81: 45016 | I81: 45382 | J81: 45747 | K81: 46112
A82: Cash from Operating Activity | B82: 689.36 | C82: 354.41 | D82: -917.94 | E82: 373.43 | F82: 1151.29 | G82: -1575.19 | H82: -4404.81 | I82: -1252.67 | J82: 3502.92 | K82: 1866.59
A83: Cash from Investing Activity | B83: -708.97 | C83: -1095.17 | D83: -1103.63 | E83: -1090.15 | F83: -882.37 | G83: -1470.91 | H83: -1307.76 | I83: -1481.36 | J83: -2898.96 | K83: -2964.47
A84: Cash from Financing Activity | B84: -58.93 | C84: 896.54 | D84: 2209.77 | E84: 1619.17 | F84: 263.5 | G84: 2918.02 | H84: 6118.08 | I84: 3238.64 | J84: 1155.24 | K84: 909.33
A85: Net Cash Flow | B85: -78.54 | C85: 155.78 | D85: 188.2 | E85: 902.45 | F85: 532.42 | G85: -128.08 | H85: 405.51 | I85: 504.61 | J85: 1759.2 | K85: -188.55
A90: PRICE: | B90: 430.8 | C90: 619.3 | D90: 470.9 | E90: 297.55 | F90: 585.05 | G90: 625.65 | H90: 1077.2 | I90: 2151.85 | J90: 2419.85 | K90: 3363.8
A92: DERIVED:
A93: Adjusted Equity Shares in Cr | B93: 47.51 | C93: 47.51 | D93: 47.51 | E93: 47.51 | F93: 47.51 | G93: 47.51 | H93: 47.51 | I93: 47.51 | J93: 47.51 | K93: 47.51

Sheet Cash Flow Sheet
B2: Cash Flow Statements
B3: Years | C3: =IFERROR('Historical FS'!C3,0) -> 17 | D3: =IFERROR('Historical FS'!D3,0) -> 18 | E3: =IFERROR('Historical FS'!E3,0) -> 19 | F3: =IFERROR('Historical FS'!F3,0) -> 20 | G3: =IFERROR('Historical FS'!G3,0) -> 21 | H3: =IFERROR('Historical FS'!H3,0) -> 22 | I3: =IFERROR('Historical FS'!I3,0) -> 23 | J3: =IFERROR('Historical FS'!J3,0) -> 24 | ... L3: =IFERROR('Historical FS'!L3,0) -> 26
B4: Cash from Operating Activities | C4: 689 | D4: 354 | E4: -918 | F4: 373 | G4: 1151 | H4: -1575 | I4: -4405 | J4: -1253 | K4: 3503 | L4: 1867
B5: Profit from operations | C5: 924 | D5: 1332 | E5: 1666 | F5: 1497 | G5: 1559 | H5: 1919 | I5: 2931 | J5: 3974 | K5: 4966 | L5: 6507
B6: Receivables | C6: -214 | D6: -348 | E6: -483 | F6: 130 | G6: 399 | H6: -143 | I6: -95 | J6: -590 | K6: 110 | L6: -875
B7: Inventory | C7: -279 | D7: 106 | E7: -235 | F7: 103 | G7: -179 | H7: -275 | I7: -314 | J7: -327 | K7: -168 | L7: -43
B8: Payables | C8: 328 | D8: 578 | E8: 509 | F8: 22 | G8: 1114 | H8: 366 | I8: 517 | J8: 1538 | K8: 924 | L8: 2274
B9: Loans Advances | C9: 0 | D9: -839 | E9: -2127 | F9: -1178 | G9: -1701 | H9: -2860 | I9: -6531 | J9: -4925 | K9: -829 | L9: -3987
B10: Other WC items | C10: 67 | D10: -148 | E10: 69 | F10: 40 | G10: 210 | H10: -217 | I10: -305 | J10: 37 | K10: -354 | L10: -384
B11: Working capital changes | C11: -98 | D11: -652 | E11: -2267 | F11: -881 | G11: -157 | H11: -3128 | I11: -6727 | J11: -4268 | K11: -316 | L11: -3015
B12: Direct taxes | C12: -137 | D12: -326 | E12: -317 | F12: -242 | G12: -251 | H12: -366 | I12: -608 | J12: -959 | K12: -1147 | L12: -1626
B13: Cash from Investing Activity - | C13: -709 | D13: -1095 | E13: -1104 | F13: -1090 | G13: -882 | H13: -1471 | I13: -1308 | J13: -1481 | K13: -2899 | L13: -2964
B14: Fixed assets purchased | C14: -590 | D14: -859 | E14: -816 | F14: -1021 | G14: -928 | H14: -970 | I14: -1341 | J14: -1145 | K14: -2478 | L14: -3235
B15: Fixed assets sold | C15: 8 | D15: 24 | E15: 10 | F15: 30 | G15: 3 | H15: 14 | I15: 22 | J15: 35 | K15: 19 | L15: 89
... B36: CFO/OP | C36: 0.95 | D36: 0.43 | E36: -0.28 | F36: 0.27 | G36: 0.63 | H36: -0.44 | I36: -0.94 | J36: -0.05 | K36: 0.71 | L36: 0.42
B38: Source: Screener.in

Sheet Historical FS
B1: ₹ in Crores
B2: ="Historical Financial Statement - "&'Data Sheet'!B1 -> Historical Financial Statement - TVS MOTOR COMPANY LTD
B3: Years | C3: =IFERROR(17,0) -> 17 | D3: =IFERROR(C3+1,0) -> 18 | E3: =IFERROR(D3+1,0) -> 19 | F3: =IFERROR(E3+1,0) -> 20 | G3: =IFERROR(F3+1,0) -> 21 | H3: =IFERROR(G3+1,0) -> 22 | I3: =IFERROR(H3+1,0) -> 23 | J3: =IFERROR(I3+1,0) -> 24 | K3: =IFERROR(J3+1,0) -> 25 | L3: =IFERROR(K3+1,0) -> 26
A4: # | B4: Income Statement
B5: Sales | C5: =IFERROR('Data Sheet'!B17,0) -> 12462.62 | D5: =IFERROR('Data Sheet'!C17,0) -> 16340.25 | E5: =IFERROR('Data Sheet'!D17,0) -> 20159.99 | F5: =IFERROR('Data Sheet'!E17,0) -> 18849.31 | G5: =IFERROR('Data Sheet'!F17,0) -> 19420.82 | H5: =IFERROR('Data Sheet'!G17,0) -> 24355.31 | I5: =IFERROR('Data Sheet'!H17,0) -> 31973.99 | J5: =IFERROR('Data Sheet'!I17,0) -> 38778.82 | ... L5: =IFERROR('Data Sheet'!K17,0) -> 56069.52
B6: Sales Growth | D6: =D5/C5-1 -> 0.31114084 | E6: =E5/D5-1 -> 0.23376264 | F6: =F5/E5-1 -> -0.065013921 | G6: =G5/F5-1 -> 0.030319943 | H6: =H5/G5-1 -> 0.25408247 | I6: =I5/H5-1 -> 0.31281392 | J6: =J5/I5-1 -> 0.21282392 | K6: =K5/J5-1 -> 0.13693532 | L6: =L5/K5-1 -> 0.27173461
B8: COGS | C8: =IFERROR(SUM('Data Sheet'!B18:B22),0) -> 10113.59 | D8: =IFERROR(SUM('Data Sheet'!C18:C22),0) -> 12658.63 | E8: =IFERROR(SUM('Data Sheet'!D18:D22),0) -> 15835.99 | F8: =IFERROR(SUM('Data Sheet'!E18:E22),0) -> 14109.47 | G8: =IFERROR(SUM('Data Sheet'!F18:F22),0) -> 14853.58 | H8: =IFERROR(SUM('Data Sheet'!G18:G22),0) -> 19190.23 | I8: =IFERROR(SUM('Data Sheet'!H18:H22),0) -> 24361.34 | J8: =IFERROR(SUM('Data Sheet'!I18:I22),0) -> 28564.68 | ... L8: =IFERROR(SUM('Data Sheet'!K18:K22),0) -> 39002.68
B9: COGS % Sales | C9: =C8/C5 -> 0.81151395 | D9: =D8/D5 -> 0.77469011 | E9: =E8/E5 -> 0.78551577 | F9: =F8/F5 -> 0.7485404 | G9: =G8/G5 -> 0.76482764 | H9: =H8/H5 -> 0.78792797 | I9: =I8/I5 -> 0.76191117 | J9: =J8/J5 -> 0.73660519 | ... L9: =L8/L5 -> 0.69561287
B11: Gross Profit | C11: =C5-C8 -> 2349.03 | D11: =D5-D8 -> 3681.62 | E11: =E5-E8 -> 4324 | F11: =F5-F8 -> 4739.84 | G11: =G5-G8 -> 4567.24 | H11: =H5-H8 -> 5165.08 | I11: =I5-I8 -> 7612.65 | J11: =J5-J8 -> 10214.14 | ... L11: =L5-L8 -> 17066.84
B12: Gross Margins | C12: =C11/C5 -> 0.18848605 | D12: =D11/D5 -> 0.22530989 | E12: =E11/E5 -> 0.21448423 | F12: =F11/F5 -> 0.2514596 | G12: =G11/G5 -> 0.23517236 | H12: =H11/H5 -> 0.21207203 | I12: =I11/I5 -> 0.23808883 | J12: =J11/J5 -> 0.26339481 | ... L12: =L11/L5 -> 0.30438713
B14: Selling & General Expenses | C14: =IFERROR(SUM('Data Sheet'!B23:B24),0) -> 1575.31 | D14: =IFERROR(SUM('Data Sheet'!C23:C24),0) -> 2042.22 | E14: =IFERROR(SUM('Data Sheet'!D23:D24),0) -> 2318.86 | F14: =IFERROR(SUM('Data Sheet'!E23:E24),0) -> 2461.92 | G14: =IFERROR(SUM('Data Sheet'!F23:F24),0) -> 2335.58 | H14: =IFERROR(SUM('Data Sheet'!G23:G24),0) -> 2931.25 | I14: =IFERROR(SUM('Data Sheet'!H23:H24),0) -> 3867.86 | J14: =IFERROR(SUM('Data Sheet'!I23:I24),0) -> 5426.33 | ... L14: =IFERROR(SUM('Data Sheet'!K23:K24),0) -> 7956.47
B15: S&G Exp % Sales | C15: =C14/C5 -> 0.12640279 | D15: =D14/D5 -> 0.12498095 | E15: =E14/E5 -> 0.11502287 | F15: =F14/F5 -> 0.13061062 | G15: =G14/G5 -> 0.12026166 | H15: =H14/H5 -> 0.12035363 | I15: =I14/I5 -> 0.12096895 | J15: =J14/J5 -> 0.13993025 | ... L15: =L14/L5 -> 0.14190366
B17: EBITDA | C17: =C11-C14 -> 773.72 | D17: =D11-D14 -> 1639.4 | E17: =E11-E14 -> 2005.14 | F17: =F11-F14 -> 2277.92 | G17: =G11-G14 -> 2231.66 | H17: =H11-H14 -> 2233.83 | I17: =I11-I14 -> 3744.79 | J17: =J11-J14 -> 4787.81 | ... L17: =L11-L14 -> 9110.37
B18: EBITDA % Sales | C18: =C17/C5 -> 0.062083254 | D18: =D17/D5 -> 0.10032894 | E18: =E17/E5 -> 0.099461359 | F18: =F17/F5 -> 0.12084899 | G18: =G17/G5 -> 0.1149107 | H18: =H17/H5 -> 0.091718397 | I18: =I17/I5 -> 0.11711988 | J18: =J17/J5 -> 0.12346456 | ... L18: =L17/L5 -> 0.16248347
B20: Interest | C20: =IFERROR('Data Sheet'!B27,0) -> 59.62 | D20: =IFERROR('Data Sheet'!C27,0) -> 338.22 | E20: =IFERROR('Data Sheet'!D27,0) -> 663.4 | F20: =IFERROR('Data Sheet'!E27,0) -> 854.54 | G20: =IFERROR('Data Sheet'!F27,0) -> 881.49 | H20: =IFERROR('Data Sheet'!G27,0) -> 940.22 | I20: =IFERROR('Data Sheet'!H27,0) -> 1367.89 | J20: =IFERROR('Data Sheet'!I27,0) -> 1916.6 | ... L20: =IFERROR('Data Sheet'!K27,0) -> 2229.82
B21: Interest % Sales | C21: =C20/C5 -> 0.0047839058 | D21: =D20/D5 -> 0.020698582 | E21: =E20/E5 -> 0.032906762 | F21: =F20/F5 -> 0.045335346 | G21: =G20/G5 -> 0.045388918 | H21: =H20/H5 -> 0.038604313 | I21: =I20/I5 -> 0.042781336 | J21: =J20/J5 -> 0.049423887 | ... L21: =L20/L5 -> 0.039768844
B23: Depreciation | C23: =IFERROR('Data Sheet'!B26,0) -> 316.82 | D23: =IFERROR('Data Sheet'!C26,0) -> 373.6 | E23: =IFERROR('Data Sheet'!D26,0) -> 441.71 | F23: =IFERROR('Data Sheet'!E26,0) -> 556 | G23: =IFERROR('Data Sheet'!F26,0) -> 564.82 | H23: =IFERROR('Data Sheet'!G26,0) -> 742.86 | I23: =IFERROR('Data Sheet'!H26,0) -> 858.86 | J23: =IFERROR('Data Sheet'!I26,0) -> 956.15 | ... L23: =IFERROR('Data Sheet'!K26,0) -> 1272.64
B24: Depreciation % Sales | C24: =C23/C5 -> 0.025421621 | D24: =D23/D5 -> 0.022863787 | E24: =E23/E5 -> 0.021910229 | F24: =F23/F5 -> 0.029497101 | G24: =G23/G5 -> 0.029083221 | H24: =H23/H5 -> 0.030500946 | I24: =I23/I5 -> 0.026861208 | J24: =J23/J5 -> 0.024656501 | ... L24: =L23/L5 -> 0.022697537
B26: EBIT | C26: =IFERROR(C17-C23,0) -> 456.9 | D26: =IFERROR(D17-D23,0) -> 1265.8 | E26: =IFERROR(E17-E23,0) -> 1563.43 | F26: =IFERROR(F17-F23,0) -> 1721.92 | G26: =IFERROR(G17-G23,0) -> 1666.84 | H26: =IFERROR(H17-H23,0) -> 1490.97 | I26: =IFERROR(I17-I23,0) -> 2885.93 | J26: =IFERROR(J17-J23,0) -> 3831.66 | ... L26: =IFERROR(L17-L23,0) -> 7837.73
B27: EBIT % Sales | C27: =IFERROR(C26/C5,0) -> 0.036661633 | D27: =IFERROR(D26/D5,0) -> 0.077465155 | E27: =IFERROR(E26/E5,0) -> 0.07755113 | F27: =IFERROR(F26/F5,0) -> 0.091351885 | G27: =IFERROR(G26/G5,0) -> 0.085827478 | H27: =IFERROR(H26/H5,0) -> 0.061217451 | I27: =IFERROR(I26/I5,0) -> 0.090258676 | J27: =IFERROR(J26/J5,0) -> 0.098808061 | ... L27: =IFERROR(L26/L5,0) -> 0.13978593
B29: EBT | C29: =IFERROR(C17-SUM(C20,C23),0) -> 397.28 | D29: =IFERROR(D17-SUM(D20,D23),0) -> 927.58 | E29: =IFERROR(E17-SUM(E20,E23),0) -> 900.03 | F29: =IFERROR(F17-SUM(F20,F23),0) -> 867.38 | G29: =IFERROR(G17-SUM(G20,G23),0) -> 785.35 | H29: =IFERROR(H17-SUM(H20,H23),0) -> 550.75 | I29: =IFERROR(I17-SUM(I20,I23),0) -> 1518.04 | J29: =IFERROR(J17-SUM(J20,J23),0) -> 1915.06 | ... L29: =IFERROR(L17-SUM(L20,L23),0) -> 5607.91
B30: EBT % Sales | C30: =C29/C5 -> 0.031877727 | D30: =D29/D5 -> 0.056766573 | E30: =E29/E5 -> 0.044644367 | F30: =F29/F5 -> 0.046016539 | G30: =G29/G5 -> 0.04043856 | H30: =H29/H5 -> 0.022613139 | I30: =I29/I5 -> 0.04747734 | J30: =J29/J5 -> 0.049384174 | ... L30: =L29/L5 -> 0.10001709
B32: Tax | C32: =IFERROR('Data Sheet'!B29,0) -> 148.67 | D32: =IFERROR('Data Sheet'!C29,0) -> 266.03 | E32: =IFERROR('Data Sheet'!D29,0) -> 357.45 | F32: =IFERROR('Data Sheet'!E29,0) -> 218.62 | G32: =IFERROR('Data Sheet'!F29,0) -> 214.13 | H32: =IFERROR('Data Sheet'!G29,0) -> 335.91 | I32: =IFERROR('Data Sheet'!H29,0) -> 626.57 | J32: =IFERROR('Data Sheet'!I29,0) -> 914.04 | ... L32: =IFERROR('Data Sheet'!K29,0) -> 1635.31
B33: Effective Tax Rate | C33: =C32/C29 -> 0.37421969 | D33: =D32/D29 -> 0.28680006 | E33: =E32/E29 -> 0.39715343 | F33: =F32/F29 -> 0.25204639 | G33: =G32/G29 -> 0.2726555 | H33: =H32/H29 -> 0.60991375 | I33: =I32/I29 -> 0.41274933 | J33: =J32/J29 -> 0.47729053 | ... L33: =L32/L29 -> 0.29160775
B35: Net Profit | C35: =IFERROR('Data Sheet'!B30,0) -> 511.24 | D35: =IFERROR('Data Sheet'!C30,0) -> 652.35 | E35: =IFERROR('Data Sheet'!D30,0) -> 704.67 | F35: =IFERROR('Data Sheet'!E30,0) -> 624.62 | G35: =IFERROR('Data Sheet'!F30,0) -> 594.26 | H35: =IFERROR('Data Sheet'!G30,0) -> 756.82 | I35: =IFERROR('Data Sheet'!H30,0) -> 1328.67 | J35: =IFERROR('Data Sheet'!I30,0) -> 1686.37 | ... L35: =IFERROR('Data Sheet'!K30,0) -> 3018.33
B36: Net Margins | C36: =C35/C5 -> 0.041021872 | D36: =D35/D5 -> 0.03992289 | E36: =E35/E5 -> 0.034953886 | F36: =F35/F5 -> 0.033137553 | G36: =G35/G5 -> 0.03059912 | H36: =H35/H5 -> 0.031074127 | I36: =I35/I5 -> 0.041554714 | J36: =J35/J5 -> 0.043486883 | ... L36: =L35/L5 -> 0.053831922
B38: No. of Equity Shares | C38: =IFERROR('Data Sheet'!B93,0) -> 47.51 | D38: =IFERROR('Data Sheet'!C93,0) -> 47.51 | E38: =IFERROR('Data Sheet'!D93,0) -> 47.51 | F38: =IFERROR('Data Sheet'!E93,0) -> 47.51 | G38: =IFERROR('Data Sheet'!F93,0) -> 47.51 | H38: =IFERROR('Data Sheet'!G93,0) -> 47.51 | I38: =IFERROR('Data Sheet'!H93,0) -> 47.51 | J38: =IFERROR('Data Sheet'!I93,0) -> 47.51 | ... L38: =IFERROR('Data Sheet'!K93,0) -> 47.51
B40: EPS | C40: =IFERROR(C35/C38,0) -> 10.760682 | D40: =IFERROR(D35/D38,0) -> 13.730794 | E40: =IFERROR(E35/E38,0) -> 14.832035 | F40: =IFERROR(F35/F38,0) -> 13.147127 | G40: =IFERROR(G35/G38,0) -> 12.508104 | H40: =IFERROR(H35/H38,0) -> 15.929699 | I40: =IFERROR(I35/I38,0) -> 27.966112 | J40: =IFERROR(J35/J38,0) -> 35.495054 | ... L40: =IFERROR(L35/L38,0) -> 63.530415
B41: EPS Growth % | D41: =IFERROR(D40/C40-1,0) -> 0.27601518 | E41: =IFERROR(E40/D40-1,0) -> 0.080202345 | F41: =IFERROR(F40/E40-1,0) -> -0.11359927 | G41: =IFERROR(G40/F40-1,0) -> -0.048605552 | H41: =IFERROR(H40/G40-1,0) -> 0.2735503 | I41: =IFERROR(I40/H40-1,0) -> 0.75559578 | J41: =IFERROR(J40/I40-1,0) -> 0.26921659 | K41: =IFERROR(K40/J40-1,0) -> 0.325664 | L41: =IFERROR(L40/K40-1,0) -> 0.35014493
B43: Dividend per Share | C43: =IFERROR('Data Sheet'!B31/'Historical FS'!C38,0) -> 2.5001052 | D43: =IFERROR('Data Sheet'!C31/'Historical FS'!D38,0) -> 3.2999369 | E43: =IFERROR('Data Sheet'!D31/'Historical FS'!E38,0) -> 3.4998948 | F43: =IFERROR('Data Sheet'!E31/'Historical FS'!F38,0) -> 3.4998948 | G43: =IFERROR('Data Sheet'!F31/'Historical FS'!G38,0) -> 3.4998948 | H43: =IFERROR('Data Sheet'!G31/'Historical FS'!H38,0) -> 3.7499474 | I43: =IFERROR('Data Sheet'!H31/'Historical FS'!I38,0) -> 5 | J43: =IFERROR('Data Sheet'!I31/'Historical FS'!J38,0) -> 8 | ... L43: =IFERROR('Data Sheet'!K31/'Historical FS'!L38,0) -> 12
B44: Dividend payout ratio | C44: =IFERROR(C43/C40,0) -> 0.23233706 | D44: =IFERROR(D43/D40,0) -> 0.24033111 | E44: =IFERROR(E43/E40,0) -> 0.23596861 | F44: =IFERROR(F43/F40,0) -> 0.26620986 | G44: =IFERROR(G43/G40,0) -> 0.27981018 | H44: =IFERROR(H43/H40,0) -> 0.23540604 | I44: =IFERROR(I43/I40,0) -> 0.17878781 | J44: =IFERROR(J43/J40,0) -> 0.22538352 | ... L44: =IFERROR(L43/L40,0) -> 0.18888591
B46: Retained Earnings | C46: =IFERROR(1-C44,0) -> 0.76766294 | D46: =IFERROR(1-D44,0) -> 0.75966889 | E46: =IFERROR(1-E44,0) -> 0.76403139 | F46: =IFERROR(1-F44,0) -> 0.73379014 | G46: =IFERROR(1-G44,0) -> 0.72018982 | H46: =IFERROR(1-H44,0) -> 0.76459396 | I46: =IFERROR(1-I44,0) -> 0.82121219 | J46: =IFERROR(1-J44,0) -> 0.77461648 | ... L46: =IFERROR(1-L44,0) -> 0.81111409
A48: # | B48: Balance Sheet
B49: Equity Share Capital | C49: =IFERROR('Data Sheet'!B57,0) -> 47.51 | D49: =IFERROR('Data Sheet'!C57,0) -> 47.51 | E49: =IFERROR('Data Sheet'!D57,0) -> 47.51 | F49: =IFERROR('Data Sheet'!E57,0) -> 47.51 | G49: =IFERROR('Data Sheet'!F57,0) -> 47.51 | H49: =IFERROR('Data Sheet'!G57,0) -> 47.51 | I49: =IFERROR('Data Sheet'!H57,0) -> 47.51 | J49: =IFERROR('Data Sheet'!I57,0) -> 47.51 | ... L49: =IFERROR('Data Sheet'!K57,0) -> 47.51
B50: Reserves | C50: =IFERROR('Data Sheet'!B58,0) -> 2168.53 | D50: =IFERROR('Data Sheet'!C58,0) -> 2629.69 | E50: =IFERROR('Data Sheet'!D58,0) -> 3122.66 | F50: =IFERROR('Data Sheet'!E58,0) -> 3234.59 | G50: =IFERROR('Data Sheet'!F58,0) -> 3779.1 | H50: =IFERROR('Data Sheet'!G58,0) -> 4351.94 | I50: =IFERROR('Data Sheet'!H58,0) -> 5457.49 | J50: =IFERROR('Data Sheet'!I58,0) -> 6736 | ... L50: =IFERROR('Data Sheet'!K58,0) -> 9516.74
B51: Borrowings | C51: =IFERROR('Data Sheet'!B59,0) -> 1310.8 | D51: =IFERROR('Data Sheet'!C59,0) -> 6927.54 | E51: =IFERROR('Data Sheet'!D59,0) -> 9298.05 | F51: =IFERROR('Data Sheet'!E59,0) -> 11591.45 | G51: =IFERROR('Data Sheet'!F59,0) -> 12179.16 | H51: =IFERROR('Data Sheet'!G59,0) -> 15827.21 | I51: =IFERROR('Data Sheet'!H59,0) -> 22375.58 | J51: =IFERROR('Data Sheet'!I59,0) -> 26005.7 | ... L51: =IFERROR('Data Sheet'!K59,0) -> 32791.01
B52: Other Liabilities | C52: =IFERROR('Data Sheet'!B60,0) -> 2601.12 | D52: =IFERROR('Data Sheet'!C60,0) -> 3585.56 | E52: =IFERROR('Data Sheet'!D60,0) -> 4228.27 | F52: =IFERROR('Data Sheet'!E60,0) -> 4398.62 | G52: =IFERROR('Data Sheet'!F60,0) -> 5859.3 | H52: =IFERROR('Data Sheet'!G60,0) -> 6692.44 | I52: =IFERROR('Data Sheet'!H60,0) -> 7143.96 | J52: =IFERROR('Data Sheet'!I60,0) -> 9234.79 | ... L52: =IFERROR('Data Sheet'!K60,0) -> 13790.36
B53: Total Liablities | C53: =IFERROR('Data Sheet'!B61,0) -> 6127.96 | D53: =IFERROR('Data Sheet'!C61,0) -> 13190.3 | E53: =IFERROR('Data Sheet'!D61,0) -> 16696.49 | F53: =IFERROR('Data Sheet'!E61,0) -> 19272.17 | G53: =IFERROR('Data Sheet'!F61,0) -> 21865.07 | H53: =IFERROR('Data Sheet'!G61,0) -> 26919.1 | I53: =IFERROR('Data Sheet'!H61,0) -> 35024.54 | J53: =IFERROR('Data Sheet'!I61,0) -> 42024 | ... L53: =IFERROR('Data Sheet'!K61,0) -> 56145.62
B55: Net Block | C55: =IFERROR('Data Sheet'!B62,0) -> 2362.06 | D55: =IFERROR('Data Sheet'!C62,0) -> 3093.85 | E55: =IFERROR('Data Sheet'!D62,0) -> 3366.8 | F55: =IFERROR('Data Sheet'!E62,0) -> 3810.69 | G55: =IFERROR('Data Sheet'!F62,0) -> 4221.05 | H55: =IFERROR('Data Sheet'!G62,0) -> 5974.64 | I55: =IFERROR('Data Sheet'!H62,0) -> 5748.03 | J55: =IFERROR('Data Sheet'!I62,0) -> 5890.82 | ... L55: =IFERROR('Data Sheet'!K62,0) -> 8633.95
B56: Capital Work in Progress | C56: =IFERROR('Data Sheet'!B63,0) -> 63.81 | D56: =IFERROR('Data Sheet'!C63,0) -> 313.26 | E56: =IFERROR('Data Sheet'!D63,0) -> 744.51 | F56: =IFERROR('Data Sheet'!E63,0) -> 1006.01 | G56: =IFERROR('Data Sheet'!F63,0) -> 1040.77 | H56: =IFERROR('Data Sheet'!G63,0) -> 551.53 | I56: =IFERROR('Data Sheet'!H63,0) -> 743.45 | J56: =IFERROR('Data Sheet'!I63,0) -> 1032.95 | ... L56: =IFERROR('Data Sheet'!K63,0) -> 2072.22
B57: Investments | C57: =IFERROR('Data Sheet'!B64,0) -> 1155.19 | D57: =IFERROR('Data Sheet'!C64,0) -> 421.02 | E57: =IFERROR('Data Sheet'!D64,0) -> 439.73 | F57: =IFERROR('Data Sheet'!E64,0) -> 370.91 | G57: =IFERROR('Data Sheet'!F64,0) -> 468.01 | H57: =IFERROR('Data Sheet'!G64,0) -> 604.56 | I57: =IFERROR('Data Sheet'!H64,0) -> 967.25 | J57: =IFERROR('Data Sheet'!I64,0) -> 1123.19 | ... L57: =IFERROR('Data Sheet'!K64,0) -> 1146.64
B58: Other Assets | C58: =IFERROR('Data Sheet'!B65-SUM('Data Sheet'!B67:B69),0) -> 631.97 | D58: =IFERROR('Data Sheet'!C65-SUM('Data Sheet'!C67:C69),0) -> 7062.21 | E58: =IFERROR('Data Sheet'!D65-SUM('Data Sheet'!D67:D69),0) -> 9101.5 | F58: =IFERROR('Data Sheet'!E65-SUM('Data Sheet'!E67:E69),0) -> 10334.16 | G58: =IFERROR('Data Sheet'!F65-SUM('Data Sheet'!F67:F69),0) -> 12081.7 | H58: =IFERROR('Data Sheet'!G65-SUM('Data Sheet'!G67:G69),0) -> 15433.1 | I58: =IFERROR('Data Sheet'!H65-SUM('Data Sheet'!H67:H69),0) -> 22508.77 | J58: =IFERROR('Data Sheet'!I65-SUM('Data Sheet'!I67:I69),0) -> 27463.49 | ... L58: =IFERROR('Data Sheet'!K65-SUM('Data Sheet'!K67:K69),0) -> 34678.36
B59: Total Non Current Assets | C59: =IFERROR(SUM(C55:C58),0) -> 4213.03 | D59: =IFERROR(SUM(D55:D58),0) -> 10890.34 | E59: =IFERROR(SUM(E55:E58),0) -> 13652.54 | F59: =IFERROR(SUM(F55:F58),0) -> 15521.77 | G59: =IFERROR(SUM(G55:G58),0) -> 17811.53 | H59: =IFERROR(SUM(H55:H58),0) -> 22563.83 | I59: =IFERROR(SUM(I55:I58),0) -> 29967.5 | J59: =IFERROR(SUM(J55:J58),0) -> 35510.45 | ... L59: =IFERROR(SUM(L55:L58),0) -> 46531.17
B61: Receivables | C61: {=IFERROR('Data Sheet'!B67:B69,0)} -> 701.81 | D61: {=IFERROR('Data Sheet'!C67:C69,0)} -> 1070.88 | E61: {=IFERROR('Data Sheet'!D67:D69,0)} -> 1546.07 | F61: {=IFERROR('Data Sheet'!E67:E69,0)} -> 1454.36 | G61: {=IFERROR('Data Sheet'!F67:F69,0)} -> 1029.26 | H61: {=IFERROR('Data Sheet'!G67:G69,0)} -> 1177.3 | I61: {=IFERROR('Data Sheet'!H67:H69,0)} -> 1256.42 | J61: {=IFERROR('Data Sheet'!I67:I69,0)} -> 1839.42 | ... L61: {=IFERROR('Data Sheet'!K67:K69,0)} -> 2654.13
B62: Inventory | C62: 1161.86 | D62: 1056.15 | E62: 1291.57 | F62: 1188.47 | G62: 1367.43 | H62: 1642.36 | I62: 1921.51 | J62: 2248.4 | K62: 2416.58 | L62: 2459.2
B63: Cash & Bank | C63: 51.26 | D63: 172.93 | E63: 206.31 | F63: 1107.57 | G63: 1656.85 | H63: 1535.61 | I63: 1879.11 | J63: 2425.73 | K63: 4386.24 | L63: 4501.12
B64: Total Current Assets | C64: =IFERROR(SUM(C61:C63),0) -> 1914.93 | D64: =IFERROR(SUM(D61:D63),0) -> 2299.96 | E64: =IFERROR(SUM(E61:E63),0) -> 3043.95 | F64: =IFERROR(SUM(F61:F63),0) -> 3750.4 | G64: =IFERROR(SUM(G61:G63),0) -> 4053.54 | H64: =IFERROR(SUM(H61:H63),0) -> 4355.27 | I64: =IFERROR(SUM(I61:I63),0) -> 5057.04 | J64: =IFERROR(SUM(J61:J63),0) -> 6513.55 | ... L64: =IFERROR(SUM(L61:L63),0) -> 9614.45
B66: Total Assets | C66: =IFERROR( C64+C59,0) -> 6127.96 | D66: =IFERROR( D64+D59,0) -> 13190.3 | E66: =IFERROR( E64+E59,0) -> 16696.49 | F66: =IFERROR( F64+F59,0) -> 19272.17 | G66: =IFERROR( G64+G59,0) -> 21865.07 | H66: =IFERROR( H64+H59,0) -> 26919.1 | I66: =IFERROR( I64+I59,0) -> 35024.54 | J66: =IFERROR( J64+J59,0) -> 42024 | ... L66: =IFERROR( L64+L59,0) -> 56145.62
B68: Check | C68: =C66=C53 -> TRUE | D68: =D66=D53 -> TRUE | E68: =E66=E53 -> TRUE | F68: =F66=F53 -> TRUE | G68: =G66=G53 -> TRUE | H68: =H66=H53 -> TRUE | I68: =I66=I53 -> TRUE | J68: =J66=J53 -> TRUE | ... L68: =L66=L53 -> TRUE
A70: # | B70: Cash Flow Statements
B71: Operating Activities -
B72: Profit from operations | C72: =IFERROR('Cash Flow Sheet'!C5,0) -> 924 | D72: =IFERROR('Cash Flow Sheet'!D5,0) -> 1332 | E72: =IFERROR('Cash Flow Sheet'!E5,0) -> 1666 | F72: =IFERROR('Cash Flow Sheet'!F5,0) -> 1497 | G72: =IFERROR('Cash Flow Sheet'!G5,0) -> 1559 | H72: =IFERROR('Cash Flow Sheet'!H5,0) -> 1919 | I72: =IFERROR('Cash Flow Sheet'!I5,0) -> 2931 | J72: =IFERROR('Cash Flow Sheet'!J5,0) -> 3974 | ... L72: =IFERROR('Cash Flow Sheet'!L5,0) -> 6507
B73: Receivables | C73: =IFERROR('Cash Flow Sheet'!C6,0) -> -214 | D73: =IFERROR('Cash Flow Sheet'!D6,0) -> -348 | E73: =IFERROR('Cash Flow Sheet'!E6,0) -> -483 | F73: =IFERROR('Cash Flow Sheet'!F6,0) -> 130 | G73: =IFERROR('Cash Flow Sheet'!G6,0) -> 399 | H73: =IFERROR('Cash Flow Sheet'!H6,0) -> -143 | I73: =IFERROR('Cash Flow Sheet'!I6,0) -> -95 | J73: =IFERROR('Cash Flow Sheet'!J6,0) -> -590 | ... L73: =IFERROR('Cash Flow Sheet'!L6,0) -> -875
B74: Inventory | C74: =IFERROR('Cash Flow Sheet'!C7,0) -> -279 | D74: =IFERROR('Cash Flow Sheet'!D7,0) -> 106 | E74: =IFERROR('Cash Flow Sheet'!E7,0) -> -235 | F74: =IFERROR('Cash Flow Sheet'!F7,0) -> 103 | G74: =IFERROR('Cash Flow Sheet'!G7,0) -> -179 | H74: =IFERROR('Cash Flow Sheet'!H7,0) -> -275 | I74: =IFERROR('Cash Flow Sheet'!I7,0) -> -314 | J74: =IFERROR('Cash Flow Sheet'!J7,0) -> -327 | ... L74: =IFERROR('Cash Flow Sheet'!L7,0) -> -43
B75: Payables | C75: =IFERROR('Cash Flow Sheet'!C8,0) -> 328 | D75: =IFERROR('Cash Flow Sheet'!D8,0) -> 578 | E75: =IFERROR('Cash Flow Sheet'!E8,0) -> 509 | F75: =IFERROR('Cash Flow Sheet'!F8,0) -> 22 | G75: =IFERROR('Cash Flow Sheet'!G8,0) -> 1114 | H75: =IFERROR('Cash Flow Sheet'!H8,0) -> 366 | I75: =IFERROR('Cash Flow Sheet'!I8,0) -> 517 | J75: =IFERROR('Cash Flow Sheet'!J8,0) -> 1538 | ... L75: =IFERROR('Cash Flow Sheet'!L8,0) -> 2274
B76: Loans Advances | C76: =IFERROR('Cash Flow Sheet'!C9,0) -> 0 | D76: =IFERROR('Cash Flow Sheet'!D9,0) -> -839 | E76: =IFERROR('Cash Flow Sheet'!E9,0) -> -2127 | F76: =IFERROR('Cash Flow Sheet'!F9,0) -> -1178 | G76: =IFERROR('Cash Flow Sheet'!G9,0) -> -1701 | H76: =IFERROR('Cash Flow Sheet'!H9,0) -> -2860 | I76: =IFERROR('Cash Flow Sheet'!I9,0) -> -6531 | J76: =IFERROR('Cash Flow Sheet'!J9,0) -> -4925 | ... L76: =IFERROR('Cash Flow Sheet'!L9,0) -> -3987
B77: Other WC items | C77: =IFERROR('Cash Flow Sheet'!C10,0) -> 67 | D77: =IFERROR('Cash Flow Sheet'!D10,0) -> -148 | E77: =IFERROR('Cash Flow Sheet'!E10,0) -> 69 | F77: =IFERROR('Cash Flow Sheet'!F10,0) -> 40 | G77: =IFERROR('Cash Flow Sheet'!G10,0) -> 210 | H77: =IFERROR('Cash Flow Sheet'!H10,0) -> -217 | I77: =IFERROR('Cash Flow Sheet'!I10,0) -> -305 | J77: =IFERROR('Cash Flow Sheet'!J10,0) -> 37 | ... L77: =IFERROR('Cash Flow Sheet'!L10,0) -> -384
B78: Working capital changes | C78: =IFERROR('Cash Flow Sheet'!C11,0) -> -98 | D78: =IFERROR('Cash Flow Sheet'!D11,0) -> -652 | E78: =IFERROR('Cash Flow Sheet'!E11,0) -> -2267 | F78: =IFERROR('Cash Flow Sheet'!F11,0) -> -881 | G78: =IFERROR('Cash Flow Sheet'!G11,0) -> -157 | H78: =IFERROR('Cash Flow Sheet'!H11,0) -> -3128 | I78: =IFERROR('Cash Flow Sheet'!I11,0) -> -6727 | J78: =IFERROR('Cash Flow Sheet'!J11,0) -> -4268 | ... L78: =IFERROR('Cash Flow Sheet'!L11,0) -> -3015
B79: Direct taxes | C79: =IFERROR('Cash Flow Sheet'!C12,0) -> -137 | D79: =IFERROR('Cash Flow Sheet'!D12,0) -> -326 | E79: =IFERROR('Cash Flow Sheet'!E12,0) -> -317 | F79: =IFERROR('Cash Flow Sheet'!F12,0) -> -242 | G79: =IFERROR('Cash Flow Sheet'!G12,0) -> -251 | H79: =IFERROR('Cash Flow Sheet'!H12,0) -> -366 | I79: =IFERROR('Cash Flow Sheet'!I12,0) -> -608 | J79: =IFERROR('Cash Flow Sheet'!J12,0) -> -959 | ... L79: =IFERROR('Cash Flow Sheet'!L12,0) -> -1626
B80: Cash from Operating Activities | C80: =IFERROR(SUM(C72:C77,C79),0) -> 689 | D80: =IFERROR(SUM(D72:D77,D79),0) -> 355 | E80: =IFERROR(SUM(E72:E77,E79),0) -> -918 | F80: =IFERROR(SUM(F72:F77,F79),0) -> 372 | G80: =IFERROR(SUM(G72:G77,G79),0) -> 1151 | H80: =IFERROR(SUM(H72:H77,H79),0) -> -1576 | I80: =IFERROR(SUM(I72:I77,I79),0) -> -4405 | J80: =IFERROR(SUM(J72:J77,J79),0) -> -1252 | ... L80: =IFERROR(SUM(L72:L77,L79),0) -> 1866
B82: Investing Activities -
B83: Fixed assets purchased | C83: =IFERROR('Cash Flow Sheet'!C14,0) -> -590 | D83: =IFERROR('Cash Flow Sheet'!D14,0) -> -859 | E83: =IFERROR('Cash Flow Sheet'!E14,0) -> -816 | F83: =IFERROR('Cash Flow Sheet'!F14,0) -> -1021 | G83: =IFERROR('Cash Flow Sheet'!G14,0) -> -928 | H83: =IFERROR('Cash Flow Sheet'!H14,0) -> -970 | I83: =IFERROR('Cash Flow Sheet'!I14,0) -> -1341 | J83: =IFERROR('Cash Flow Sheet'!J14,0) -> -1145 | ... L83: =IFERROR('Cash Flow Sheet'!L14,0) -> -3235
B84: Fixed assets sold | C84: =IFERROR('Cash Flow Sheet'!C15,0) -> 8 | D84: =IFERROR('Cash Flow Sheet'!D15,0) -> 24 | E84: =IFERROR('Cash Flow Sheet'!E15,0) -> 10 | F84: =IFERROR('Cash Flow Sheet'!F15,0) -> 30 | G84: =IFERROR('Cash Flow Sheet'!G15,0) -> 3 | H84: =IFERROR('Cash Flow Sheet'!H15,0) -> 14 | I84: =IFERROR('Cash Flow Sheet'!I15,0) -> 22 | J84: =IFERROR('Cash Flow Sheet'!J15,0) -> 35 | ... L84: =IFERROR('Cash Flow Sheet'!L15,0) -> 89
B85: Capital WIP | C85: =IFERROR('Cash Flow Sheet'!C16,0) -> -43 | D85: =IFERROR('Cash Flow Sheet'!D16,0) -> -247 | E85: =IFERROR('Cash Flow Sheet'!E16,0) -> -324 | F85: =IFERROR('Cash Flow Sheet'!F16,0) -> 0 | G85: =IFERROR('Cash Flow Sheet'!G16,0) -> 0 | H85: =IFERROR('Cash Flow Sheet'!H16,0) -> 0 | I85: =IFERROR('Cash Flow Sheet'!I16,0) -> 0 | J85: =IFERROR('Cash Flow Sheet'!J16,0) -> 0 | ... L85: =IFERROR('Cash Flow Sheet'!L16,0) -> 0
B86: Investments purchased | C86: =IFERROR('Cash Flow Sheet'!C17,0) -> -72 | D86: =IFERROR('Cash Flow Sheet'!D17,0) -> -41 | E86: =IFERROR('Cash Flow Sheet'!E17,0) -> -32 | F86: =IFERROR('Cash Flow Sheet'!F17,0) -> -94 | G86: =IFERROR('Cash Flow Sheet'!G17,0) -> -6 | H86: =IFERROR('Cash Flow Sheet'!H17,0) -> -147 | I86: =IFERROR('Cash Flow Sheet'!I17,0) -> -266 | J86: =IFERROR('Cash Flow Sheet'!J17,0) -> -223 | ... L86: =IFERROR('Cash Flow Sheet'!L17,0) -> -191
B87: Investments sold | C87: =IFERROR('Cash Flow Sheet'!C18,0) -> 0 | D87: =IFERROR('Cash Flow Sheet'!D18,0) -> 0 | E87: =IFERROR('Cash Flow Sheet'!E18,0) -> 3 | F87: =IFERROR('Cash Flow Sheet'!F18,0) -> 6 | G87: =IFERROR('Cash Flow Sheet'!G18,0) -> 17 | H87: =IFERROR('Cash Flow Sheet'!H18,0) -> 87 | I87: =IFERROR('Cash Flow Sheet'!I18,0) -> 0 | J87: =IFERROR('Cash Flow Sheet'!J18,0) -> 48 | ... L87: =IFERROR('Cash Flow Sheet'!L18,0) -> 335
B88: Interest received | C88: =IFERROR('Cash Flow Sheet'!C19,0) -> 48 | D88: =IFERROR('Cash Flow Sheet'!D19,0) -> 3 | E88: =IFERROR('Cash Flow Sheet'!E19,0) -> 4 | F88: =IFERROR('Cash Flow Sheet'!F19,0) -> 27 | G88: =IFERROR('Cash Flow Sheet'!G19,0) -> 29 | H88: =IFERROR('Cash Flow Sheet'!H19,0) -> 8 | I88: =IFERROR('Cash Flow Sheet'!I19,0) -> 13 | J88: =IFERROR('Cash Flow Sheet'!J19,0) -> 24 | ... L88: =IFERROR('Cash Flow Sheet'!L19,0) -> 42
B89: Dividends Received | C89: =IFERROR('Cash Flow Sheet'!C20,0) -> 1 | D89: =IFERROR('Cash Flow Sheet'!D20,0) -> 1 | E89: =IFERROR('Cash Flow Sheet'!E20,0) -> 1 | F89: =IFERROR('Cash Flow Sheet'!F20,0) -> 1 | G89: =IFERROR('Cash Flow Sheet'!G20,0) -> 0 | H89: =IFERROR('Cash Flow Sheet'!H20,0) -> 4 | I89: =IFERROR('Cash Flow Sheet'!I20,0) -> 0 | J89: =IFERROR('Cash Flow Sheet'!J20,0) -> 0 | ... L89: =IFERROR('Cash Flow Sheet'!L20,0) -> 0
B90: Investment in Group Companies | C90: =IFERROR('Cash Flow Sheet'!C21,0) -> 0 | D90: =IFERROR('Cash Flow Sheet'!D21,0) -> 0 | E90: =IFERROR('Cash Flow Sheet'!E21,0) -> 0 | F90: =IFERROR('Cash Flow Sheet'!F21,0) -> 0 | G90: =IFERROR('Cash Flow Sheet'!G21,0) -> 0 | H90: =IFERROR('Cash Flow Sheet'!H21,0) -> 0 | I90: =IFERROR('Cash Flow Sheet'!I21,0) -> -87 | J90: =IFERROR('Cash Flow Sheet'!J21,0) -> -388 | ... L90: =IFERROR('Cash Flow Sheet'!L21,0) -> -4
B91: Redemption and Cancelling of Shares | C91: =IFERROR('Cash Flow Sheet'!C22,0) -> 0 | D91: =IFERROR('Cash Flow Sheet'!D22,0) -> 34 | E91: =IFERROR('Cash Flow Sheet'!E22,0) -> 0 | F91: =IFERROR('Cash Flow Sheet'!F22,0) -> 0 | G91: =IFERROR('Cash Flow Sheet'!G22,0) -> 0 | H91: =IFERROR('Cash Flow Sheet'!H22,0) -> 0 | I91: =IFERROR('Cash Flow Sheet'!I22,0) -> 0 | J91: =IFERROR('Cash Flow Sheet'!J22,0) -> 169 | ... L91: =IFERROR('Cash Flow Sheet'!L22,0) -> 0
B92: Acquisition of companies | C92: =IFERROR('Cash Flow Sheet'!C23,0) -> -40 | D92: =IFERROR('Cash Flow Sheet'!D23,0) -> -33 | E92: =IFERROR('Cash Flow Sheet'!E23,0) -> -6 | F92: =IFERROR('Cash Flow Sheet'!F23,0) -> -39 | G92: =IFERROR('Cash Flow Sheet'!G23,0) -> -53 | H92: =IFERROR('Cash Flow Sheet'!H23,0) -> -75 | I92: =IFERROR('Cash Flow Sheet'!I23,0) -> 0 | J92: =IFERROR('Cash Flow Sheet'!J23,0) -> 0 | ... L92: =IFERROR('Cash Flow Sheet'!L23,0) -> 0
B93: Other investing items | C93: =IFERROR('Cash Flow Sheet'!C24,0) -> -21 | D93: =IFERROR('Cash Flow Sheet'!D24,0) -> 23 | E93: =IFERROR('Cash Flow Sheet'!E24,0) -> 56 | F93: =IFERROR('Cash Flow Sheet'!F24,0) -> 0 | G93: =IFERROR('Cash Flow Sheet'!G24,0) -> 55 | H93: =IFERROR('Cash Flow Sheet'!H24,0) -> -392 | I93: =IFERROR('Cash Flow Sheet'!I24,0) -> 351 | J93: =IFERROR('Cash Flow Sheet'!J24,0) -> 0 | ... L93: =IFERROR('Cash Flow Sheet'!L24,0) -> 0
B94: Cash from investing activities | C94: =IFERROR(SUM(C83:C93),0) -> -709 | D94: =IFERROR(SUM(D83:D93),0) -> -1095 | E94: =IFERROR(SUM(E83:E93),0) -> -1104 | F94: =IFERROR(SUM(F83:F93),0) -> -1090 | G94: =IFERROR(SUM(G83:G93),0) -> -883 | H94: =IFERROR(SUM(H83:H93),0) -> -1471 | I94: =IFERROR(SUM(I83:I93),0) -> -1308 | J94: =IFERROR(SUM(J83:J93),0) -> -1480 | ... L94: =IFERROR(SUM(L83:L93),0) -> -2964
B96: Financing Activity -
B97: Proceeds from shares | C97: =IFERROR('Cash Flow Sheet'!C26,0) -> 0 | D97: =IFERROR('Cash Flow Sheet'!D26,0) -> 0 | E97: =IFERROR('Cash Flow Sheet'!E26,0) -> 0 | F97: =IFERROR('Cash Flow Sheet'!F26,0) -> 0 | G97: =IFERROR('Cash Flow Sheet'!G26,0) -> 0 | H97: =IFERROR('Cash Flow Sheet'!H26,0) -> 0 | I97: =IFERROR('Cash Flow Sheet'!I26,0) -> 0 | J97: =IFERROR('Cash Flow Sheet'!J26,0) -> 0 | ... L97: =IFERROR('Cash Flow Sheet'!L26,0) -> 6
B98: Proceeds from borrowings | C98: =IFERROR('Cash Flow Sheet'!C27,0) -> 274 | D98: =IFERROR('Cash Flow Sheet'!D27,0) -> 694 | E98: =IFERROR('Cash Flow Sheet'!E27,0) -> 2507 | F98: =IFERROR('Cash Flow Sheet'!F27,0) -> 1972 | G98: =IFERROR('Cash Flow Sheet'!G27,0) -> 1271 | H98: =IFERROR('Cash Flow Sheet'!H27,0) -> 3353 | I98: =IFERROR('Cash Flow Sheet'!I27,0) -> 6588 | J98: =IFERROR('Cash Flow Sheet'!J27,0) -> 3844 | ... L98: =IFERROR('Cash Flow Sheet'!L27,0) -> 3556
B99: Repayment of borrowings | C99: =IFERROR('Cash Flow Sheet'!C28,0) -> 0 | D99: =IFERROR('Cash Flow Sheet'!D28,0) -> 0 | E99: =IFERROR('Cash Flow Sheet'!E28,0) -> 0 | F99: =IFERROR('Cash Flow Sheet'!F28,0) -> 0 | G99: =IFERROR('Cash Flow Sheet'!G28,0) -> -673 | H99: =IFERROR('Cash Flow Sheet'!H28,0) -> 0 | I99: =IFERROR('Cash Flow Sheet'!I28,0) -> 0 | J99: =IFERROR('Cash Flow Sheet'!J28,0) -> -182 | ... L99: =IFERROR('Cash Flow Sheet'!L28,0) -> -1448
B100: Proceeds from deposits | C100: =IFERROR('Cash Flow Sheet'!C29,0) -> 0 | D100: =IFERROR('Cash Flow Sheet'!D29,0) -> 6 | E100: =IFERROR('Cash Flow Sheet'!E29,0) -> 28 | F100: =IFERROR('Cash Flow Sheet'!F29,0) -> 15 | G100: =IFERROR('Cash Flow Sheet'!G29,0) -> 0 | H100: =IFERROR('Cash Flow Sheet'!H29,0) -> 0 | I100: =IFERROR('Cash Flow Sheet'!I29,0) -> 0 | J100: =IFERROR('Cash Flow Sheet'!J29,0) -> 0 | ... L100: =IFERROR('Cash Flow Sheet'!L29,0) -> 0
B101: Interest Paid | C101: =IFERROR('Cash Flow Sheet'!C30,0) -> -59 | D101: =IFERROR('Cash Flow Sheet'!D30,0) -> -62 | E101: =IFERROR('Cash Flow Sheet'!E30,0) -> -125 | F101: =IFERROR('Cash Flow Sheet'!F30,0) -> -124 | G101: =IFERROR('Cash Flow Sheet'!G30,0) -> -127 | H101: =IFERROR('Cash Flow Sheet'!H30,0) -> -156 | I101: =IFERROR('Cash Flow Sheet'!I30,0) -> -112 | J101: =IFERROR('Cash Flow Sheet'!J30,0) -> -284 | ... L101: =IFERROR('Cash Flow Sheet'!L30,0) -> -249
B102: Dividends paid | C102: =IFERROR('Cash Flow Sheet'!C31,0) -> -143 | D102: =IFERROR('Cash Flow Sheet'!D31,0) -> -189 | E102: =IFERROR('Cash Flow Sheet'!E31,0) -> -200 | F102: =IFERROR('Cash Flow Sheet'!F31,0) -> -200 | G102: =IFERROR('Cash Flow Sheet'!G31,0) -> -100 | H102: =IFERROR('Cash Flow Sheet'!H31,0) -> -190 | I102: =IFERROR('Cash Flow Sheet'!I31,0) -> -292 | J102: =IFERROR('Cash Flow Sheet'!J31,0) -> -380 | ... L102: =IFERROR('Cash Flow Sheet'!L31,0) -> -570
B103: Financial liabilities | C103: =IFERROR('Cash Flow Sheet'!C32,0) -> 0 | D103: =IFERROR('Cash Flow Sheet'!D32,0) -> 0 | E103: =IFERROR('Cash Flow Sheet'!E32,0) -> 0 | F103: =IFERROR('Cash Flow Sheet'!F32,0) -> -43 | G103: =IFERROR('Cash Flow Sheet'!G32,0) -> -52 | H103: =IFERROR('Cash Flow Sheet'!H32,0) -> -82 | I103: =IFERROR('Cash Flow Sheet'!I32,0) -> -128 | J103: =IFERROR('Cash Flow Sheet'!J32,0) -> -196 | ... L103: =IFERROR('Cash Flow Sheet'!L32,0) -> -414
B104: Other financing items | C104: =IFERROR('Cash Flow Sheet'!C33,0) -> -131 | D104: =IFERROR('Cash Flow Sheet'!D33,0) -> 447 | E104: =IFERROR('Cash Flow Sheet'!E33,0) -> 0 | F104: =IFERROR('Cash Flow Sheet'!F33,0) -> 0 | G104: =IFERROR('Cash Flow Sheet'!G33,0) -> -55 | H104: =IFERROR('Cash Flow Sheet'!H33,0) -> -7 | I104: =IFERROR('Cash Flow Sheet'!I33,0) -> 62 | J104: =IFERROR('Cash Flow Sheet'!J33,0) -> 436 | ... L104: =IFERROR('Cash Flow Sheet'!L33,0) -> 28
B105: Cash from Financing Activities | C105: =IFERROR(SUM(C97:C104),0) -> -59 | D105: =IFERROR(SUM(D97:D104),0) -> 896 | E105: =IFERROR(SUM(E97:E104),0) -> 2210 | F105: =IFERROR(SUM(F97:F104),0) -> 1620 | G105: =IFERROR(SUM(G97:G104),0) -> 264 | H105: =IFERROR(SUM(H97:H104),0) -> 2918 | I105: =IFERROR(SUM(I97:I104),0) -> 6118 | J105: =IFERROR(SUM(J97:J104),0) -> 3238 | ... L105: =IFERROR(SUM(L97:L104),0) -> 909
B107: Net Cash Flow | C107: =IFERROR(C80+C94+C105,0) -> -79 | D107: =IFERROR(D80+D94+D105,0) -> 156 | E107: =IFERROR(E80+E94+E105,0) -> 188 | F107: =IFERROR(F80+F94+F105,0) -> 902 | G107: =IFERROR(G80+G94+G105,0) -> 532 | H107: =IFERROR(H80+H94+H105,0) -> -129 | I107: =IFERROR(I80+I94+I105,0) -> 405 | J107: =IFERROR(J80+J94+J105,0) -> 506 | ... L107: =IFERROR(L80+L94+L105,0) -> -189

Sheet Ratio Analysis
B3: Years | C3: =IFERROR('Historical FS'!C3,0) -> 17 | D3: =IFERROR('Historical FS'!D3,0) -> 18 | E3: =IFERROR('Historical FS'!E3,0) -> 19 | F3: =IFERROR('Historical FS'!F3,0) -> 20 | G3: =IFERROR('Historical FS'!G3,0) -> 21 | H3: =IFERROR('Historical FS'!H3,0) -> 22 | I3: =IFERROR('Historical FS'!I3,0) -> 23 | J3: =IFERROR('Historical FS'!J3,0) -> 24 | ... L3: =IFERROR('Historical FS'!L3,0) -> 26 | M3: Mean | N3: Median
B5: Sales Growth | D5: =IFERROR('Historical FS'!D6,0) -> 0.31114084 | E5: =IFERROR('Historical FS'!E6,0) -> 0.23376264 | F5: =IFERROR('Historical FS'!F6,0) -> -0.065013921 | G5: =IFERROR('Historical FS'!G6,0) -> 0.030319943 | H5: =IFERROR('Historical FS'!H6,0) -> 0.25408247 | I5: =IFERROR('Historical FS'!I6,0) -> 0.31281392 | J5: =IFERROR('Historical FS'!J6,0) -> 0.21282392 | K5: =IFERROR('Historical FS'!K6,0) -> 0.13693532 | L5: =IFERROR('Historical FS'!L6,0) -> 0.27173461 | M5: =IFERROR(AVERAGE(D5:L5),0) -> 0.1887333 | N5: =IFERROR(MEDIAN(C5:L5),0) -> 0.23376264
B6: EBITDA Growth | D6: =IFERROR('Historical FS'!D17/'Historical FS'!C17-1,0) -> 1.1188544 | E6: =IFERROR('Historical FS'!E17/'Historical FS'!D17-1,0) -> 0.22309381 | F6: =IFERROR('Historical FS'!F17/'Historical FS'!E17-1,0) -> 0.13604038 | G6: =IFERROR('Historical FS'!G17/'Historical FS'!F17-1,0) -> -0.020308 | H6: =IFERROR('Historical FS'!H17/'Historical FS'!G17-1,0) -> 0.00097237034 | I6: =IFERROR('Historical FS'!I17/'Historical FS'!H17-1,0) -> 0.67639883 | J6: =IFERROR('Historical FS'!J17/'Historical FS'!I17-1,0) -> 0.27852563 | K6: =IFERROR('Historical FS'!K17/'Historical FS'!J17-1,0) -> 0.34281853 | L6: =IFERROR('Historical FS'!L17/'Historical FS'!K17-1,0) -> 0.41703893 | M6: =IFERROR(AVERAGE(D6:L6),0) -> 0.35260387 | N6: =IFERROR(MEDIAN(C6:L6),0) -> 0.27852563
B7: Net Profit Growth | D7: =IFERROR('Historical FS'!D35/'Historical FS'!C35-1,0) -> 0.27601518 | E7: =IFERROR('Historical FS'!E35/'Historical FS'!D35-1,0) -> 0.080202345 | F7: =IFERROR('Historical FS'!F35/'Historical FS'!E35-1,0) -> -0.11359927 | G7: =IFERROR('Historical FS'!G35/'Historical FS'!F35-1,0) -> -0.048605552 | H7: =IFERROR('Historical FS'!H35/'Historical FS'!G35-1,0) -> 0.2735503 | I7: =IFERROR('Historical FS'!I35/'Historical FS'!H35-1,0) -> 0.75559578 | J7: =IFERROR('Historical FS'!J35/'Historical FS'!I35-1,0) -> 0.26921659 | K7: =IFERROR('Historical FS'!K35/'Historical FS'!J35-1,0) -> 0.325664 | L7: =IFERROR('Historical FS'!L35/'Historical FS'!K35-1,0) -> 0.35014493 | M7: =IFERROR(AVERAGE(D7:L7),0) -> 0.24090937 | N7: =IFERROR(MEDIAN(C7:L7),0) -> 0.2735503
B8: Dividend Growth | D8: =IFERROR('Historical FS'!D43/'Historical FS'!C43-1,0) -> 0.31991918 | E8: =IFERROR('Historical FS'!E43/'Historical FS'!D43-1,0) -> 0.060594464 | F8: =IFERROR('Historical FS'!F43/'Historical FS'!E43-1,0) -> 0 | G8: =IFERROR('Historical FS'!G43/'Historical FS'!F43-1,0) -> 0 | H8: =IFERROR('Historical FS'!H43/'Historical FS'!G43-1,0) -> 0.071445754 | I8: =IFERROR('Historical FS'!I43/'Historical FS'!H43-1,0) -> 0.33335204 | J8: =IFERROR('Historical FS'!J43/'Historical FS'!I43-1,0) -> 0.6 | K8: =IFERROR('Historical FS'!K43/'Historical FS'!J43-1,0) -> 0.25 | L8: =IFERROR('Historical FS'!L43/'Historical FS'!K43-1,0) -> 0.2 | M8: =IFERROR(AVERAGE(D8:L8),0) -> 0.20392349 | N8: =IFERROR(MEDIAN(C8:L8),0) -> 0.2
B10: Gross Margin | C10: =IFERROR('Historical FS'!C11/'Historical FS'!C5,0) -> 0.18848605 | D10: =IFERROR('Historical FS'!D11/'Historical FS'!D5,0) -> 0.22530989 | E10: =IFERROR('Historical FS'!E11/'Historical FS'!E5,0) -> 0.21448423 | F10: =IFERROR('Historical FS'!F11/'Historical FS'!F5,0) -> 0.2514596 | G10: =IFERROR('Historical FS'!G11/'Historical FS'!G5,0) -> 0.23517236 | H10: =IFERROR('Historical FS'!H11/'Historical FS'!H5,0) -> 0.21207203 | I10: =IFERROR('Historical FS'!I11/'Historical FS'!I5,0) -> 0.23808883 | J10: =IFERROR('Historical FS'!J11/'Historical FS'!J5,0) -> 0.26339481 | ... L10: =IFERROR('Historical FS'!L11/'Historical FS'!L5,0) -> 0.30438713 | M10: =IFERROR(AVERAGE(C10:L10),0) -> 0.24316335 | N10: =IFERROR(MEDIAN(C10:L10),0) -> 0.2366306
B11: EBITDA Margin | C11: =IFERROR('Historical FS'!C18,0) -> 0.062083254 | D11: =IFERROR('Historical FS'!D18,0) -> 0.10032894 | E11: =IFERROR('Historical FS'!E18,0) -> 0.099461359 | F11: =IFERROR('Historical FS'!F18,0) -> 0.12084899 | G11: =IFERROR('Historical FS'!G18,0) -> 0.1149107 | H11: =IFERROR('Historical FS'!H18,0) -> 0.091718397 | I11: =IFERROR('Historical FS'!I18,0) -> 0.11711988 | J11: =IFERROR('Historical FS'!J18,0) -> 0.12346456 | ... L11: =IFERROR('Historical FS'!L18,0) -> 0.16248347 | M11: =IFERROR(AVERAGE(C11:L11),0) -> 0.11382418 | N11: =IFERROR(MEDIAN(C11:L11),0) -> 0.11601529
B12: EBIT Margin | C12: =IFERROR('Historical FS'!C27,0) -> 0.036661633 | D12: =IFERROR('Historical FS'!D27,0) -> 0.077465155 | E12: =IFERROR('Historical FS'!E27,0) -> 0.07755113 | F12: =IFERROR('Historical FS'!F27,0) -> 0.091351885 | G12: =IFERROR('Historical FS'!G27,0) -> 0.085827478 | H12: =IFERROR('Historical FS'!H27,0) -> 0.061217451 | I12: =IFERROR('Historical FS'!I27,0) -> 0.090258676 | J12: =IFERROR('Historical FS'!J27,0) -> 0.098808061 | ... L12: =IFERROR('Historical FS'!L27,0) -> 0.13978593 | M12: =IFERROR(AVERAGE(C12:L12),0) -> 0.088103493 | N12: =IFERROR(MEDIAN(C12:L12),0) -> 0.088043077
B13: EBT Margin | C13: =IFERROR('Historical FS'!C30,0) -> 0.031877727 | D13: =IFERROR('Historical FS'!D30,0) -> 0.056766573 | E13: =IFERROR('Historical FS'!E30,0) -> 0.044644367 | F13: =IFERROR('Historical FS'!F30,0) -> 0.046016539 | G13: =IFERROR('Historical FS'!G30,0) -> 0.04043856 | H13: =IFERROR('Historical FS'!H30,0) -> 0.022613139 | I13: =IFERROR('Historical FS'!I30,0) -> 0.04747734 | J13: =IFERROR('Historical FS'!J30,0) -> 0.049384174 | ... L13: =IFERROR('Historical FS'!L30,0) -> 0.10001709 | M13: =IFERROR(AVERAGE(C13:L13),0) -> 0.051386521 | N13: =IFERROR(MEDIAN(C13:L13),0) -> 0.046746939
B14: Net Profit Margin | C14: =IFERROR('Historical FS'!C36,0) -> 0.041021872 | D14: =IFERROR('Historical FS'!D36,0) -> 0.03992289 | E14: =IFERROR('Historical FS'!E36,0) -> 0.034953886 | F14: =IFERROR('Historical FS'!F36,0) -> 0.033137553 | G14: =IFERROR('Historical FS'!G36,0) -> 0.03059912 | H14: =IFERROR('Historical FS'!H36,0) -> 0.031074127 | I14: =IFERROR('Historical FS'!I36,0) -> 0.041554714 | J14: =IFERROR('Historical FS'!J36,0) -> 0.043486883 | ... L14: =IFERROR('Historical FS'!L36,0) -> 0.053831922 | M14: =IFERROR(AVERAGE(C14:L14),0) -> 0.040028857 | N14: =IFERROR(MEDIAN(C14:L14),0) -> 0.040472381
B16: Sales Expenses % Sales | C16: =IFERROR('Historical FS'!C15,0) -> 0.12640279 | D16: =IFERROR('Historical FS'!D15,0) -> 0.12498095 | E16: =IFERROR('Historical FS'!E15,0) -> 0.11502287 | F16: =IFERROR('Historical FS'!F15,0) -> 0.13061062 | G16: =IFERROR('Historical FS'!G15,0) -> 0.12026166 | H16: =IFERROR('Historical FS'!H15,0) -> 0.12035363 | I16: =IFERROR('Historical FS'!I15,0) -> 0.12096895 | J16: =IFERROR('Historical FS'!J15,0) -> 0.13993025 | ... L16: =IFERROR('Historical FS'!L15,0) -> 0.14190366 | M16: =IFERROR(AVERAGE(C16:L16),0) -> 0.12933916 | N16: =IFERROR(MEDIAN(C16:L16),0) -> 0.12569187
B17: Depreciation % Sales | C17: =IFERROR('Historical FS'!C24,0) -> 0.025421621 | D17: =IFERROR('Historical FS'!D24,0) -> 0.022863787 | E17: =IFERROR('Historical FS'!E24,0) -> 0.021910229 | F17: =IFERROR('Historical FS'!F24,0) -> 0.029497101 | G17: =IFERROR('Historical FS'!G24,0) -> 0.029083221 | H17: =IFERROR('Historical FS'!H24,0) -> 0.030500946 | I17: =IFERROR('Historical FS'!I24,0) -> 0.026861208 | J17: =IFERROR('Historical FS'!J24,0) -> 0.024656501 | ... L17: =IFERROR('Historical FS'!L24,0) -> 0.022697537 | M17: =IFERROR(AVERAGE(C17:L17),0) -> 0.02572069 | N17: =IFERROR(MEDIAN(C17:L17),0) -> 0.025039061
B18: Operating Income % Sales | C18: =C12 -> 0.036661633 | D18: =D12 -> 0.077465155 | E18: =E12 -> 0.07755113 | F18: =F12 -> 0.091351885 | G18: =G12 -> 0.085827478 | H18: =H12 -> 0.061217451 | I18: =I12 -> 0.090258676 | J18: =J12 -> 0.098808061 | ... L18: =L12 -> 0.13978593 | M18: =IFERROR(AVERAGE(C18:L18),0) -> 0.088103493 | N18: =IFERROR(MEDIAN(C18:L18),0) -> 0.088043077
B20: Return on Capital Employed | C20: =IFERROR('Historical FS'!C26/SUM('Historical FS'!C49:C51),0) -> 0.1295494 | D20: =IFERROR('Historical FS'!D26/SUM('Historical FS'!D49:D51),0) -> 0.1317891 | E20: =IFERROR('Historical FS'!E26/SUM('Historical FS'!E49:E51),0) -> 0.1253932 | F20: =IFERROR('Historical FS'!F26/SUM('Historical FS'!F49:F51),0) -> 0.11577061 | G20: =IFERROR('Historical FS'!G26/SUM('Historical FS'!G49:G51),0) -> 0.10413994 | H20: =IFERROR('Historical FS'!H26/SUM('Historical FS'!H49:H51),0) -> 0.073713109 | I20: =IFERROR('Historical FS'!I26/SUM('Historical FS'!I49:I51),0) -> 0.1035104 | J20: =IFERROR('Historical FS'!J26/SUM('Historical FS'!J49:J51),0) -> 0.11685734 | ... L20: =IFERROR('Historical FS'!L26/SUM('Historical FS'!L49:L51),0) -> 0.18504738 | M20: =IFERROR(AVERAGE(C20:L20),0) -> 0.12308337 | N20: =IFERROR(MEDIAN(C20:L20),0) -> 0.12112527
B21: Retained Earnings % | C21: =IFERROR('Historical FS'!C46,0) -> 0.76766294 | D21: =IFERROR('Historical FS'!D46,0) -> 0.75966889 | E21: =IFERROR('Historical FS'!E46,0) -> 0.76403139 | F21: =IFERROR('Historical FS'!F46,0) -> 0.73379014 | G21: =IFERROR('Historical FS'!G46,0) -> 0.72018982 | H21: =IFERROR('Historical FS'!H46,0) -> 0.76459396 | I21: =IFERROR('Historical FS'!I46,0) -> 0.82121219 | J21: =IFERROR('Historical FS'!J46,0) -> 0.77461648 | ... L21: =IFERROR('Historical FS'!L46,0) -> 0.81111409 | M21: =IFERROR(AVERAGE(C21:L21),0) -> 0.77043604 | N21: =IFERROR(MEDIAN(C21:L21),0) -> 0.76612845
B22: Return on Equity % | C22: =IFERROR('Historical FS'!C35/SUM('Historical FS'!C49:C50),0) -> 0.23069981 | D22: =IFERROR('Historical FS'!D35/SUM('Historical FS'!D49:D50),0) -> 0.24366876 | E22: =IFERROR('Historical FS'!E35/SUM('Historical FS'!E49:E50),0) -> 0.22228145 | F22: =IFERROR('Historical FS'!F35/SUM('Historical FS'!F49:F50),0) -> 0.19031108 | G22: =IFERROR('Historical FS'!G35/SUM('Historical FS'!G49:G50),0) -> 0.15529672 | H22: =IFERROR('Historical FS'!H35/SUM('Historical FS'!H49:H50),0) -> 0.17202605 | I22: =IFERROR('Historical FS'!I35/SUM('Historical FS'!I49:I50),0) -> 0.24135695 | J22: =IFERROR('Historical FS'!J35/SUM('Historical FS'!J49:J50),0) -> 0.24859844 | ... L22: =IFERROR('Historical FS'!L35/SUM('Historical FS'!L49:L50),0) -> 0.3155846 | M22: =IFERROR(AVERAGE(C22:L22),0) -> 0.22827264 | N22: =IFERROR(MEDIAN(C22:L22),0) -> 0.23602838
B23: Self Sustained Growth Rate | C23: =IFERROR(C21*C22,0) -> 0.17709969 | D23: =IFERROR(D21*D22,0) -> 0.18510758 | E23: =IFERROR(E21*E22,0) -> 0.16983001 | F23: =IFERROR(F21*F22,0) -> 0.1396484 | G23: =IFERROR(G21*G22,0) -> 0.11184312 | H23: =IFERROR(H21*H22,0) -> 0.13153008 | I23: =IFERROR(I21*I22,0) -> 0.19820527 | J23: =IFERROR(J21*J22,0) -> 0.19256845 | ... L23: =IFERROR(L21*L22,0) -> 0.25597512 | M23: =IFERROR(AVERAGE(C23:L23),0) -> 0.17688383 | N23: =IFERROR(MEDIAN(C23:L23),0) -> 0.18110363
B24: Interest Coverage Ratio | C24: =IFERROR('Historical FS'!C26/'Historical FS'!C20,0) -> 7.6635357 | D24: =IFERROR('Historical FS'!D26/'Historical FS'!D20,0) -> 3.7425344 | E24: =IFERROR('Historical FS'!E26/'Historical FS'!E20,0) -> 2.3566928 | F24: =IFERROR('Historical FS'!F26/'Historical FS'!F20,0) -> 2.0150256 | G24: =IFERROR('Historical FS'!G26/'Historical FS'!G20,0) -> 1.8909347 | H24: =IFERROR('Historical FS'!H26/'Historical FS'!H20,0) -> 1.5857672 | I24: =IFERROR('Historical FS'!I26/'Historical FS'!I20,0) -> 2.1097676 | J24: =IFERROR('Historical FS'!J26/'Historical FS'!J20,0) -> 1.9991965 | ... L24: =IFERROR('Historical FS'!L26/'Historical FS'!L20,0) -> 3.5149608 | M24: =IFERROR(AVERAGE(C24:L24),0) -> 2.9450301 | N24: =IFERROR(MEDIAN(C24:L24),0) -> 2.2332302
B26: Debtor Turnover Ratio | C26: =IFERROR('Historical FS'!C5/'Historical FS'!C61,0) -> 17.757826 | D26: =IFERROR('Historical FS'!D5/'Historical FS'!D61,0) -> 15.258712 | E26: =IFERROR('Historical FS'!E5/'Historical FS'!E61,0) -> 13.039507 | F26: =IFERROR('Historical FS'!F5/'Historical FS'!F61,0) -> 12.960553 | G26: =IFERROR('Historical FS'!G5/'Historical FS'!G61,0) -> 18.868721 | H26: =IFERROR('Historical FS'!H5/'Historical FS'!H61,0) -> 20.687429 | I26: =IFERROR('Historical FS'!I5/'Historical FS'!I61,0) -> 25.448489 | J26: =IFERROR('Historical FS'!J5/'Historical FS'!J61,0) -> 21.082091 | ... L26: =IFERROR('Historical FS'!L5/'Historical FS'!L61,0) -> 21.125386 | M26: =IFERROR(AVERAGE(C26:L26),0) -> 19.191039 | N26: =IFERROR(MEDIAN(C26:L26),0) -> 19.778075
B27: Creditor Turnover Ratio | C27: =IFERROR('Historical FS'!C5/'Historical FS'!C52,0) -> 4.7912515 | D27: =IFERROR('Historical FS'!D5/'Historical FS'!D52,0) -> 4.5572379 | E27: =IFERROR('Historical FS'!E5/'Historical FS'!E52,0) -> 4.7679051 | F27: =IFERROR('Historical FS'!F5/'Historical FS'!F52,0) -> 4.2852781 | G27: =IFERROR('Historical FS'!G5/'Historical FS'!G52,0) -> 3.314529 | H27: =IFERROR('Historical FS'!H5/'Historical FS'!H52,0) -> 3.6392272 | I27: =IFERROR('Historical FS'!I5/'Historical FS'!I52,0) -> 4.4756676 | J27: =IFERROR('Historical FS'!J5/'Historical FS'!J52,0) -> 4.1992097 | ... L27: =IFERROR('Historical FS'!L5/'Historical FS'!L52,0) -> 4.0658489 | M27: =IFERROR(AVERAGE(C27:L27),0) -> 4.2279649 | N27: =IFERROR(MEDIAN(C27:L27),0) -> 4.2422439
B28: Fixed Asset Turnover | C28: =IFERROR('Historical FS'!C5/'Historical FS'!C55,0) -> 5.2761657 | D28: =IFERROR('Historical FS'!D5/'Historical FS'!D55,0) -> 5.2815263 | E28: =IFERROR('Historical FS'!E5/'Historical FS'!E55,0) -> 5.9878787 | F28: =IFERROR('Historical FS'!F5/'Historical FS'!F55,0) -> 4.9464296 | G28: =IFERROR('Historical FS'!G5/'Historical FS'!G55,0) -> 4.6009453 | H28: =IFERROR('Historical FS'!H5/'Historical FS'!H55,0) -> 4.0764481 | I28: =IFERROR('Historical FS'!I5/'Historical FS'!I55,0) -> 5.5625997 | J28: =IFERROR('Historical FS'!J5/'Historical FS'!J55,0) -> 6.5829239 | ... L28: =IFERROR('Historical FS'!L5/'Historical FS'!L55,0) -> 6.4940751 | M28: =IFERROR(AVERAGE(C28:L28),0) -> 5.4576446 | N28: =IFERROR(MEDIAN(C28:L28),0) -> 5.422063
B29: Capital Turnover Ratio | C29: =IFERROR('Historical FS'!C5/SUM('Historical FS'!C49:C50),0) -> 5.6238245 | D29: =IFERROR('Historical FS'!D5/SUM('Historical FS'!D49:D50),0) -> 6.103485 | E29: =IFERROR('Historical FS'!E5/SUM('Historical FS'!E49:E50),0) -> 6.3592773 | F29: =IFERROR('Historical FS'!F5/SUM('Historical FS'!F49:F50),0) -> 5.7430639 | G29: =IFERROR('Historical FS'!G5/SUM('Historical FS'!G49:G50),0) -> 5.0752023 | H29: =IFERROR('Historical FS'!H5/SUM('Historical FS'!H49:H50),0) -> 5.5359897 | I29: =IFERROR('Historical FS'!I5/SUM('Historical FS'!I49:I50),0) -> 5.8081726 | J29: =IFERROR('Historical FS'!J5/SUM('Historical FS'!J49:J50),0) -> 5.7166305 | ... L29: =IFERROR('Historical FS'!L5/SUM('Historical FS'!L49:L50),0) -> 5.8624064 | M29: =IFERROR(AVERAGE(C29:L29),0) -> 5.7012933 | N29: =IFERROR(MEDIAN(C29:L29),0) -> 5.7298472
B32: Debtor Days | C32: =IFERROR(365/C26,0) -> 20.554318 | D32: =IFERROR(365/D26,0) -> 23.92076 | E32: =IFERROR(365/E26,0) -> 27.991857 | F32: =IFERROR(365/F26,0) -> 28.162378 | G32: =IFERROR(365/G26,0) -> 19.344183 | H32: =IFERROR(365/H26,0) -> 17.643565 | I32: =IFERROR(365/I26,0) -> 14.342699 | J32: =IFERROR(365/J26,0) -> 17.313273 | ... L32: =IFERROR(365/L26,0) -> 17.277791 | M32: =IFERROR(AVERAGE(C32:L32),0) -> 20.076329 | N32: =IFERROR(MEDIAN(C32:L32),0) -> 18.493874
B33: Payable Days | C33: =IFERROR(365/C27,0) -> 76.180514 | D33: =IFERROR(365/D27,0) -> 80.092373 | E33: =IFERROR(365/E27,0) -> 76.553537 | F33: =IFERROR(365/F27,0) -> 85.175335 | G33: =IFERROR(365/G27,0) -> 110.12123 | H33: =IFERROR(365/H27,0) -> 100.29602 | I33: =IFERROR(365/I27,0) -> 81.55208 | J33: =IFERROR(365/J27,0) -> 86.921117 | ... L33: =IFERROR(365/L27,0) -> 89.772151 | M33: =IFERROR(AVERAGE(C33:L33),0) -> 87.391199 | N33: =IFERROR(MEDIAN(C33:L33),0) -> 86.048226
B34: Inventory Days | C34: =IFERROR('Historical FS'!C62/'Historical FS'!C8*365,0) -> 41.931589 | D34: =IFERROR('Historical FS'!D62/'Historical FS'!D8*365,0) -> 30.453118 | E34: =IFERROR('Historical FS'!E62/'Historical FS'!E8*365,0) -> 29.769092 | F34: =IFERROR('Historical FS'!F62/'Historical FS'!F8*365,0) -> 30.744709 | G34: =IFERROR('Historical FS'!G62/'Historical FS'!G8*365,0) -> 33.602132 | H34: =IFERROR('Historical FS'!H62/'Historical FS'!H8*365,0) -> 31.237843 | I34: =IFERROR('Historical FS'!I62/'Historical FS'!I8*365,0) -> 28.789514 | J34: =IFERROR('Historical FS'!J62/'Historical FS'!J8*365,0) -> 28.730096 | ... L34: =IFERROR('Historical FS'!L62/'Historical FS'!L8*365,0) -> 23.014008 | M34: =IFERROR(AVERAGE(C34:L34),0) -> 30.680254 | N34: =IFERROR(MEDIAN(C34:L34),0) -> 30.111105
B35: Cash Conversion Cycle | C35: =IFERROR(C32+C34-C33,0) -> -13.694607 | D35: =IFERROR(D32+D34-D33,0) -> -25.718495 | E35: =IFERROR(E32+E34-E33,0) -> -18.792588 | F35: =IFERROR(F32+F34-F33,0) -> -26.268248 | G35: =IFERROR(G32+G34-G33,0) -> -57.174911 | H35: =IFERROR(H32+H34-H33,0) -> -51.414609 | I35: =IFERROR(I32+I34-I33,0) -> -38.419867 | J35: =IFERROR(J32+J34-J33,0) -> -40.877748 | ... N35: =IFERROR(N32+N34-N33,0) -> -37.443247
B37: CFO/Sales | C37: =IFERROR('Historical FS'!C80/'Historical FS'!C5,0) -> 0.055285325 | D37: =IFERROR('Historical FS'!D80/'Historical FS'!D5,0) -> 0.021725494 | E37: =IFERROR('Historical FS'!E80/'Historical FS'!E5,0) -> -0.045535737 | F37: =IFERROR('Historical FS'!F80/'Historical FS'!F5,0) -> 0.01973547 | G37: =IFERROR('Historical FS'!G80/'Historical FS'!G5,0) -> 0.059266293 | H37: =IFERROR('Historical FS'!H80/'Historical FS'!H5,0) -> -0.064708682 | I37: =IFERROR('Historical FS'!I80/'Historical FS'!I5,0) -> -0.13776823 | J37: =IFERROR('Historical FS'!J80/'Historical FS'!J5,0) -> -0.032285665 | ... L37: =IFERROR('Historical FS'!L80/'Historical FS'!L5,0) -> 0.033280114 | M37: =IFERROR(AVERAGE(C37:L37),0) -> -0.0011575392 | N37: =IFERROR(MEDIAN(C37:L37),0) -> 0.020730482
B38: CFO/Total Assets | C38: =IFERROR('Historical FS'!C80/'Historical FS'!C66,0) -> 0.11243546 | D38: =IFERROR('Historical FS'!D80/'Historical FS'!D66,0) -> 0.026913717 | E38: =IFERROR('Historical FS'!E80/'Historical FS'!E66,0) -> -0.054981616 | F38: =IFERROR('Historical FS'!F80/'Historical FS'!F66,0) -> 0.019302445 | G38: =IFERROR('Historical FS'!G80/'Historical FS'!G66,0) -> 0.052641039 | H38: =IFERROR('Historical FS'!H80/'Historical FS'!H66,0) -> -0.058545791 | I38: =IFERROR('Historical FS'!I80/'Historical FS'!I66,0) -> -0.12576896 | J38: =IFERROR('Historical FS'!J80/'Historical FS'!J66,0) -> -0.0297925 | ... L38: =IFERROR('Historical FS'!L80/'Historical FS'!L66,0) -> 0.033235006 | M38: =IFERROR(AVERAGE(C38:L38),0) -> 0.0048931655 | N38: =IFERROR(MEDIAN(C38:L38),0) -> 0.023108081
B39: CFO/Total Debt | C39: =IFERROR('Historical FS'!C80/'Historical FS'!C51,0) -> 0.5256332 | D39: =IFERROR('Historical FS'!D80/'Historical FS'!D51,0) -> 0.051244742 | E39: =IFERROR('Historical FS'!E80/'Historical FS'!E51,0) -> -0.098730379 | F39: =IFERROR('Historical FS'!F80/'Historical FS'!F51,0) -> 0.03209262 | G39: =IFERROR('Historical FS'!G80/'Historical FS'!G51,0) -> 0.094505697 | H39: =IFERROR('Historical FS'!H80/'Historical FS'!H51,0) -> -0.099575352 | I39: =IFERROR('Historical FS'!I80/'Historical FS'!I51,0) -> -0.19686641 | J39: =IFERROR('Historical FS'!J80/'Historical FS'!J51,0) -> -0.048143292 | ... L39: =IFERROR('Historical FS'!L80/'Historical FS'!L51,0) -> 0.056905841 | M39: =IFERROR(AVERAGE(C39:L39),0) -> 0.043947695 | N39: =IFERROR(MEDIAN(C39:L39),0) -> 0.041668681

Sheet Drivers
B1: ="Drivers - "& 'Data Sheet'!B1 -> Drivers - TVS MOTOR COMPANY LTD
B2: Years | C2: =IFERROR('Historical FS'!H3,0) -> 22 | D2: =IFERROR('Historical FS'!I3,0) -> 23 | E2: =IFERROR('Historical FS'!J3,0) -> 24 | F2: =IFERROR('Historical FS'!K3,0) -> 25 | G2: =IFERROR('Historical FS'!L3,0) -> 26 | H2: 3-Year AVG | I2: 5-Year AVG
B4: Sales Growth % | C4: =IFERROR('Historical FS'!H6,0) -> 0.25408247 | D4: =IFERROR('Historical FS'!I6,0) -> 0.31281392 | E4: =IFERROR('Historical FS'!J6,0) -> 0.21282392 | F4: =IFERROR('Historical FS'!K6,0) -> 0.13693532 | G4: =IFERROR('Historical FS'!L6,0) -> 0.27173461 | H4: =IFERROR(AVERAGE(E4:G4),0) -> 0.20716462 | I4: =IFERROR(AVERAGE(C4:G4),0) -> 0.23767805
B6: COGS % Sales | C6: =IFERROR('Historical FS'!H9,0) -> 0.78792797 | D6: =IFERROR('Historical FS'!I9,0) -> 0.76191117 | E6: =IFERROR('Historical FS'!J9,0) -> 0.73660519 | F6: =IFERROR('Historical FS'!K9,0) -> 0.70122146 | G6: =IFERROR('Historical FS'!L9,0) -> 0.69561287 | H6: =IFERROR(AVERAGE(E6:G6),0) -> 0.71114651 | I6: =IFERROR(AVERAGE(C6:G6),0) -> 0.73665573
B8: S&G Exp % Sales | C8: =IFERROR('Historical FS'!H15,0) -> 0.12035363 | D8: =IFERROR('Historical FS'!I15,0) -> 0.12096895 | E8: =IFERROR('Historical FS'!J15,0) -> 0.13993025 | F8: =IFERROR('Historical FS'!K15,0) -> 0.15295626 | G8: =IFERROR('Historical FS'!L15,0) -> 0.14190366 | H8: =IFERROR(AVERAGE(E8:G8),0) -> 0.14493006 | I8: =IFERROR(AVERAGE(C8:G8),0) -> 0.13522255
B10: Depreciation % Sales | C10: =IFERROR('Historical FS'!H24,0) -> 0.030500946 | D10: =IFERROR('Historical FS'!I24,0) -> 0.026861208 | E10: =IFERROR('Historical FS'!J24,0) -> 0.024656501 | F10: =IFERROR('Historical FS'!K24,0) -> 0.023714753 | G10: =IFERROR('Historical FS'!L24,0) -> 0.022697537 | H10: =IFERROR(AVERAGE(E10:G10),0) -> 0.023689597 | I10: =IFERROR(AVERAGE(C10:G10),0) -> 0.025686189
B12: Cost of Debt % | C12: =IFERROR('Historical FS'!H20/AVERAGE('Historical FS'!G51:H51),0) -> 0.067143296 | D12: =IFERROR('Historical FS'!I20/AVERAGE('Historical FS'!H51:I51),0) -> 0.071612047 | E12: =IFERROR('Historical FS'!J20/AVERAGE('Historical FS'!I51:J51),0) -> 0.079228991 | F12: =IFERROR('Historical FS'!K20/AVERAGE('Historical FS'!J51:K51),0) -> 0.076655593 | G12: =IFERROR('Historical FS'!L20/AVERAGE('Historical FS'!K51:L51),0) -> 0.072632905 | H12: =IFERROR(AVERAGE(E12:G12),0) -> 0.076172496 | I12: =IFERROR(AVERAGE(C12:G12),0) -> 0.073454566
B14: Effective Tax Rate | C14: =IFERROR('Historical FS'!H33,0) -> 0.60991375 | D14: =IFERROR('Historical FS'!I33,0) -> 0.41274933 | E14: =IFERROR('Historical FS'!J33,0) -> 0.47729053 | F14: =IFERROR('Historical FS'!K33,0) -> 0.35116325 | G14: =IFERROR('Historical FS'!L33,0) -> 0.29160775 | H14: =IFERROR(AVERAGE(E14:G14),0) -> 0.37335384 | I14: =IFERROR(AVERAGE(C14:G14),0) -> 0.42854492
B16: Dividend Payout | C16: =IFERROR('Historical FS'!H44,0) -> 0.23540604 | D16: =IFERROR('Historical FS'!I44,0) -> 0.17878781 | E16: =IFERROR('Historical FS'!J44,0) -> 0.22538352 | F16: =IFERROR('Historical FS'!K44,0) -> 0.21251946 | G16: =IFERROR('Historical FS'!L44,0) -> 0.18888591 | H16: =IFERROR(AVERAGE(E16:G16),0) -> 0.20892963 | I16: =IFERROR(AVERAGE(C16:G16),0) -> 0.20819655
B18: Debtors Days | C18: =IFERROR('Ratio Analysis'!H32,0) -> 17.643565 | D18: =IFERROR('Ratio Analysis'!I32,0) -> 14.342699 | E18: =IFERROR('Ratio Analysis'!J32,0) -> 17.313273 | F18: =IFERROR('Ratio Analysis'!K32,0) -> 14.21247 | G18: =IFERROR('Ratio Analysis'!L32,0) -> 17.277791 | H18: =IFERROR(AVERAGE(E18:G18),0) -> 16.267845 | I18: =IFERROR(AVERAGE(C18:G18),0) -> 16.15796
B20: Inventory Days | C20: =IFERROR('Ratio Analysis'!H34,0) -> 31.237843 | D20: =IFERROR('Ratio Analysis'!I34,0) -> 28.789514 | E20: =IFERROR('Ratio Analysis'!J34,0) -> 28.730096 | F20: =IFERROR('Ratio Analysis'!K34,0) -> 28.530442 | G20: =IFERROR('Ratio Analysis'!L34,0) -> 23.014008 | H20: =IFERROR(AVERAGE(E20:G20),0) -> 26.758182 | I20: =IFERROR(AVERAGE(C20:G20),0) -> 28.060381
B22: Payable Days | C22: =IFERROR('Ratio Analysis'!H33,0) -> 100.29602 | D22: =IFERROR('Ratio Analysis'!I33,0) -> 81.55208 | E22: =IFERROR('Ratio Analysis'!J33,0) -> 86.921117 | F22: =IFERROR('Ratio Analysis'!K33,0) -> 87.247638 | G22: =IFERROR('Ratio Analysis'!L33,0) -> 89.772151 | H22: =IFERROR(AVERAGE(E22:G22),0) -> 87.980302 | I22: =IFERROR(AVERAGE(C22:G22),0) -> 89.157801
B24: Capex % Sales | C24: =IFERROR(-'Historical FS'!H83/'Historical FS'!H5,0) -> 0.039827044 | D24: =IFERROR(-'Historical FS'!I83/'Historical FS'!I5,0) -> 0.04194034 | E24: =IFERROR(-'Historical FS'!J83/'Historical FS'!J5,0) -> 0.029526427 | F24: =IFERROR(-'Historical FS'!K83/'Historical FS'!K5,0) -> 0.056204483 | G24: =IFERROR(-'Historical FS'!L83/'Historical FS'!L5,0) -> 0.057696231 | H24: =IFERROR(AVERAGE(E24:G24),0) -> 0.047809047 | I24: =IFERROR(AVERAGE(C24:G24),0) -> 0.045038905
B26: Net Borrowing Growth % | C26: =IFERROR('Historical FS'!H51/'Historical FS'!G51-1,0) -> 0.29953215 | D26: =IFERROR('Historical FS'!I51/'Historical FS'!H51-1,0) -> 0.41374127 | E26: =IFERROR('Historical FS'!J51/'Historical FS'!I51-1,0) -> 0.16223579 | F26: =IFERROR('Historical FS'!K51/'Historical FS'!J51-1,0) -> 0.10009383 | G26: =IFERROR('Historical FS'!L51/'Historical FS'!K51-1,0) -> 0.14618974 | H26: =IFERROR(AVERAGE(E26:G26),0) -> 0.13617312 | I26: =IFERROR(AVERAGE(C26:G26),0) -> 0.22435856

Sheet Forecast
B2: ₹ in Crores
B3: ="Forecast- "&'Data Sheet'!B1 -> Forecast- TVS MOTOR COMPANY LTD
B4: Year | C4: Hist.Ref | D4: =IFERROR(27,0) -> 27 | E4: =IFERROR(D4+1,0) -> 28 | F4: =IFERROR(E4+1,0) -> 29 | G4: =IFERROR(F4+1,0) -> 30 | H4: =IFERROR(G4+1,0) -> 31
A5: # | B5: Assumptions
B7: Sales Growth % | C7: =IFERROR(Drivers!I4,0) -> 0.23767805 | D7: 0.22 | E7: 0.19 | F7: 0.16 | G7: 0.14 | H7: 0.12
B9: COGS % Sales | C9: =IFERROR(Drivers!I6,0) -> 0.73665573 | D9: 0.7 | E9: 0.702 | F9: 0.705 | G9: 0.707 | H9: 0.71
B11: S&G Exp % Sales | C11: =IFERROR(Drivers!H8,0) -> 0.14493006 | D11: 0.142 | E11: 0.14 | F11: 0.14 | G11: 0.138 | H11: 0.138
B13: Depreciation % Sales | C13: =IFERROR(Drivers!H10,0) -> 0.023689597 | D13: 0.024 | E13: 0.025 | F13: 0.026 | G13: 0.026 | H13: 0.027
B15: Cost of Debt % | C15: =IFERROR(Drivers!H12,0) -> 0.076172496 | D15: 0.072 | E15: 0.07 | F15: 0.068 | G15: 0.068 | H15: 0.068
B17: Effective Tax Rate | C17: =IFERROR(Drivers!H14,0) -> 0.37335384 | D17: 0.28 | E17: 0.27 | F17: 0.26 | G17: 0.25 | H17: 0.25
B19: Dividend Payout | C19: =IFERROR(Drivers!I16,0) -> 0.20819655 | D19: 0.2 | E19: 0.2 | F19: 0.22 | G19: 0.22 | H19: 0.25
B21: Debtors Days | C21: =IFERROR(Drivers!I18,0) -> 16.15796 | D21: 17 | E21: 16.5 | F21: 16.5 | G21: 16 | H21: 16
B23: Inventory Days | C23: =IFERROR(Drivers!H20,0) -> 26.758182 | D23: 25 | E23: 24 | F23: 23 | G23: 23 | H23: 22
B25: Payable Days | C25: =IFERROR(Drivers!I22,0) -> 89.157801 | D25: 89 | E25: 89 | F25: 90 | G25: 90 | H25: 90
B27: Capex % Sales | C27: =IFERROR(Drivers!H24,0) -> 0.047809047 | D27: 0.055 | E27: 0.055 | F27: 0.05 | G27: 0.05 | H27: 0.048
B29: Net Borrowing Growth % | C29: =IFERROR(Drivers!H26,0) -> 0.13617312 | D29: 0.12 | E29: 0.1 | F29: 0.08 | G29: 0.06 | H29: 0.05
A32: # | B32: Income Statements
B33: Sales | D33: =IFERROR('Historical FS'!L5*(1+Forecast!D7),0) -> 68404.814 | E33: =IFERROR(D33*(1+E7),0) -> 81401.729 | F33: =IFERROR(E33*(1+F7),0) -> 94426.006 | G33: =IFERROR(F33*(1+G7),0) -> 107645.65 | H33: =IFERROR(G33*(1+H7),0) -> 120563.12
B34: Sales Growth | E34: =IFERROR(E33/D33-1,0) -> 0.19 | F34: =IFERROR(F33/E33-1,0) -> 0.16 | G34: =IFERROR(G33/F33-1,0) -> 0.14 | H34: =IFERROR(H33/G33-1,0) -> 0.12
B36: COGS | D36: =D33*D9 -> 47883.37 | E36: =E33*E9 -> 57144.014 | F36: =F33*F9 -> 66570.334 | G36: =G33*G9 -> 76105.472 | H36: =H33*H9 -> 85599.818
B37: COGS % Sales | D37: =IFERROR(D36/D33,0) -> 0.7 | E37: =IFERROR(E36/E33,0) -> 0.702 | F37: =IFERROR(F36/F33,0) -> 0.705 | G37: =IFERROR(G36/G33,0) -> 0.707 | H37: =IFERROR(H36/H33,0) -> 0.71
B39: Gross Profit | D39: =IFERROR(D33-D36,0) -> 20521.444 | E39: =IFERROR(E33-E36,0) -> 24257.715 | F39: =IFERROR(F33-F36,0) -> 27855.672 | G39: =IFERROR(G33-G36,0) -> 31540.174 | H39: =IFERROR(H33-H36,0) -> 34963.306
B40: Gross Margins | D40: =IFERROR(D39/D33,0) -> 0.3 | E40: =IFERROR(E39/E33,0) -> 0.298 | F40: =IFERROR(F39/F33,0) -> 0.295 | G40: =IFERROR(G39/G33,0) -> 0.293 | H40: =IFERROR(H39/H33,0) -> 0.29
B42: Selling & General Expenses | D42: =IFERROR(D33*D11,0) -> 9713.4836 | E42: =IFERROR(E33*E11,0) -> 11396.242 | F42: =IFERROR(F33*F11,0) -> 13219.641 | G42: =IFERROR(G33*G11,0) -> 14855.099 | H42: =IFERROR(H33*H11,0) -> 16637.711
B43: S&G Exp % Sales | D43: =IFERROR(D42/D33,0) -> 0.142 | E43: =IFERROR(E42/E33,0) -> 0.14 | F43: =IFERROR(F42/F33,0) -> 0.14 | G43: =IFERROR(G42/G33,0) -> 0.138 | H43: =IFERROR(H42/H33,0) -> 0.138
B45: EBITDA | D45: =IFERROR(D39-D42,0) -> 10807.961 | E45: =IFERROR(E39-E42,0) -> 12861.473 | F45: =IFERROR(F39-F42,0) -> 14636.031 | G45: =IFERROR(G39-G42,0) -> 16685.075 | H45: =IFERROR(H39-H42,0) -> 18325.595
B46: EBITDA % Sales | D46: =IFERROR(D45/D33,0) -> 0.158 | E46: =IFERROR(E45/E33,0) -> 0.158 | F46: =IFERROR(F45/F33,0) -> 0.155 | G46: =IFERROR(G45/G33,0) -> 0.155 | H46: =IFERROR(H45/H33,0) -> 0.152
B48: Interest | D48: =IFERROR(D15*AVERAGE('Historical FS'!L51,Forecast!D81),0) -> 2502.6099 | E48: =IFERROR(E15*AVERAGE(D81,E81),0) -> 2699.3559 | F48: =IFERROR(F15*AVERAGE(E81,F81),0) -> 2856.9836 | G48: =IFERROR(G15*AVERAGE(F81,G81),0) -> 3055.8737 | H48: =IFERROR(H15*AVERAGE(G81,H81),0) -> 3223.5017
B49: Interest % Sales | D49: =IFERROR(D48/D33,0) -> 0.036585289 | E49: =IFERROR(E48/E33,0) -> 0.033160917 | F49: =IFERROR(F48/F33,0) -> 0.030256322 | G49: =IFERROR(G48/G33,0) -> 0.02838827 | H49: =IFERROR(H48/H33,0) -> 0.026737045
B51: Depreciation | D51: =IFERROR(D33*D13,0) -> 1641.7155 | E51: =IFERROR(E33*E13,0) -> 2035.0432 | F51: =IFERROR(F33*F13,0) -> 2455.0762 | G51: =IFERROR(G33*G13,0) -> 2798.7868 | H51: =IFERROR(H33*H13,0) -> 3255.2044
B52: Depreciation % Sales | D52: =IFERROR(D51/D33,0) -> 0.024 | E52: =IFERROR(E51/E33,0) -> 0.025 | F52: =IFERROR(F51/F33,0) -> 0.026 | G52: =IFERROR(G51/G33,0) -> 0.026 | H52: =IFERROR(H51/H33,0) -> 0.027
B54: EBIT | D54: =IFERROR(D45-D51,0) -> 9166.2451 | E54: =IFERROR(E45-E51,0) -> 10826.43 | F54: =IFERROR(F45-F51,0) -> 12180.955 | G54: =IFERROR(G45-G51,0) -> 13886.288 | H54: =IFERROR(H45-H51,0) -> 15070.391
B55: EBIT % Sales | D55: =IFERROR(D54/D33,0) -> 0.134 | E55: =IFERROR(E54/E33,0) -> 0.133 | F55: =IFERROR(F54/F33,0) -> 0.129 | G55: =IFERROR(G54/G33,0) -> 0.129 | H55: =IFERROR(H54/H33,0) -> 0.125
B57: EBT | D57: =IFERROR(D54-D48,0) -> 6663.6352 | E57: =IFERROR(E54-E48,0) -> 8127.074 | F57: =IFERROR(F54-F48,0) -> 9323.9711 | G57: =IFERROR(G54-G48,0) -> 10830.415 | H57: =IFERROR(H54-H48,0) -> 11846.889
B58: EBT % Sales | D58: =IFERROR(D57/D33,0) -> 0.097414711 | E58: =IFERROR(E57/E33,0) -> 0.099839083 | F58: =IFERROR(F57/F33,0) -> 0.098743678 | G58: =IFERROR(G57/G33,0) -> 0.10061173 | H58: =IFERROR(H57/H33,0) -> 0.098262955
B60: Tax | D60: =IFERROR(D57*D17,0) -> 1865.8179 | E60: =IFERROR(E57*E17,0) -> 2194.31 | F60: =IFERROR(F57*F17,0) -> 2424.2325 | G60: =IFERROR(G57*G17,0) -> 2707.6037 | H60: =IFERROR(H57*H17,0) -> 2961.7222
B61: Effective Tax Rate | D61: =IFERROR(D60/D57,0) -> 0.28 | E61: =IFERROR(E60/E57,0) -> 0.27 | F61: =IFERROR(F60/F57,0) -> 0.26 | G61: =IFERROR(G60/G57,0) -> 0.25 | H61: =IFERROR(H60/H57,0) -> 0.25
B63: Net Profit | D63: =IFERROR(D57-D60,0) -> 4797.8174 | E63: =IFERROR(E57-E60,0) -> 5932.764 | F63: =IFERROR(F57-F60,0) -> 6899.7386 | G63: =IFERROR(G57-G60,0) -> 8122.8111 | H63: =IFERROR(H57-H60,0) -> 8885.1666
B64: Net Margins | D64: =IFERROR(D63/D33,0) -> 0.070138592 | E64: =IFERROR(E63/E33,0) -> 0.072882531 | F64: =IFERROR(F63/F33,0) -> 0.073070322 | G64: =IFERROR(G63/G33,0) -> 0.075458798 | H64: =IFERROR(H63/H33,0) -> 0.073697216
B66: No. of Equity Shares | D66: =IFERROR('Historical FS'!L38,0) -> 47.51 | E66: =IFERROR(D66,0) -> 47.51 | F66: =IFERROR(E66,0) -> 47.51 | G66: =IFERROR(F66,0) -> 47.51 | H66: =IFERROR(G66,0) -> 47.51
B68: EPS | D68: =IFERROR(D63/D66,0) -> 100.98542 | E68: =IFERROR(E63/E66,0) -> 124.87401 | F68: =IFERROR(F63/F66,0) -> 145.22708 | G68: =IFERROR(G63/G66,0) -> 170.97056 | H68: =IFERROR(H63/H66,0) -> 187.01677
B69: EPS Growth % | E69: =IFERROR(E68/D68-1,0) -> 0.23655479 | F69: =IFERROR(F68/E68-1,0) -> 0.16298888 | G69: =IFERROR(G68/F68-1,0) -> 0.17726359 | H69: =IFERROR(H68/G68-1,0) -> 0.093853663
B71: Dividend per Share | D71: =IFERROR(D63*D19/D66,0) -> 20.197084 | E71: =IFERROR(E63*E19/E66,0) -> 24.974801 | F71: =IFERROR(F63*F19/F66,0) -> 31.949958 | G71: =IFERROR(G63*G19/G66,0) -> 37.613522 | H71: =IFERROR(H63*H19/H66,0) -> 46.754192
B72: Dividend payout ratio | D72: =IFERROR(D71/D68,0) -> 0.2 | E72: =IFERROR(E71/E68,0) -> 0.2 | F72: =IFERROR(F71/F68,0) -> 0.22 | G72: =IFERROR(G71/G68,0) -> 0.22 | H72: =IFERROR(H71/H68,0) -> 0.25
B74: Retained Earnings | D74: =IFERROR(D63-D71*D66,0) -> 3838.2539 | E74: =IFERROR(E63-E71*E66,0) -> 4746.2112 | F74: =IFERROR(F63-F71*F66,0) -> 5381.7961 | G74: =IFERROR(G63-G71*G66,0) -> 6335.7926 | H74: =IFERROR(H63-H71*H66,0) -> 6663.875
D75: {=IFERROR(1-D72,o)} -> 0.8 | E75: {=IFERROR(1-E72,o)} -> 0.8 | F75: {=IFERROR(1-F72,o)} -> 0.78 | G75: {=IFERROR(1-G72,o)} -> 0.78 | H75: {=IFERROR(1-H72,o)} -> 0.75
A77: # | B77: Balance Sheet
B79: Equity Share Capital | D79: =IFERROR('Historical FS'!L49,0) -> 47.51 | E79: =IFERROR(D79,0) -> 47.51 | F79: =IFERROR(E79,0) -> 47.51 | G79: =IFERROR(F79,0) -> 47.51 | H79: =IFERROR(G79,0) -> 47.51
B80: Reserves | D80: =IFERROR('Historical FS'!L50+Forecast!D74,0) -> 13354.994 | E80: =IFERROR(D80+E74,0) -> 18101.205 | F80: =IFERROR(E80+F74,0) -> 23483.001 | G80: =IFERROR(F80+G74,0) -> 29818.794 | H80: =IFERROR(G80+H74,0) -> 36482.669
B81: Borrowings | D81: =IFERROR('Historical FS'!L51*(1+Forecast!D29),0) -> 36725.931 | E81: =IFERROR(D81*(1+E29),0) -> 40398.524 | F81: =IFERROR(E81*(1+F29),0) -> 43630.406 | G81: =IFERROR(F81*(1+G29),0) -> 46248.231 | H81: =IFERROR(G81*(1+H29),0) -> 48560.642
B82: Other Liabilities | D82: =IFERROR(D33/365*D25,0) -> 16679.53 | E82: =IFERROR(E33/365*E25,0) -> 19848.641 | F82: =IFERROR(F33/365*F25,0) -> 23283.125 | G82: =IFERROR(G33/365*G25,0) -> 26542.762 | H82: =IFERROR(H33/365*H25,0) -> 29727.894
B83: Total Liablities | D83: =IFERROR(SUM(D79:D82),0) -> 66807.965 | E83: =IFERROR(SUM(E79:E82),0) -> 78395.88 | F83: =IFERROR(SUM(F79:F82),0) -> 90444.042 | G83: =IFERROR(SUM(G79:G82),0) -> 102657.3 | H83: =IFERROR(SUM(H79:H82),0) -> 114818.71
B85: Net Block | D85: =IFERROR('Historical FS'!L55+(Forecast!D33*Forecast!D27)-D51,0) -> 10754.499 | E85: =IFERROR(D85+E33*E27-E51,0) -> 13196.551 | F85: =IFERROR(E85+F33*F27-F51,0) -> 15462.775 | G85: =IFERROR(F85+G33*G27-G51,0) -> 18046.271 | H85: =IFERROR(G85+H33*H27-H51,0) -> 20578.096
B86: Capital Work in Progress | D86: =IFERROR('Historical FS'!L56,0) -> 2072.22 | E86: =IFERROR(D86,0) -> 2072.22 | F86: =IFERROR(E86,0) -> 2072.22 | G86: =IFERROR(F86,0) -> 2072.22 | H86: =IFERROR(G86,0) -> 2072.22
B87: Investments | D87: =IFERROR('Historical FS'!L57,0) -> 1146.64 | E87: =IFERROR(D87,0) -> 1146.64 | F87: =IFERROR(E87,0) -> 1146.64 | G87: =IFERROR(F87,0) -> 1146.64 | H87: =IFERROR(G87,0) -> 1146.64
B88: Other Assets | D88: =IFERROR('Historical FS'!$L$58/'Historical FS'!$L$5*Forecast!D33,0) -> 42307.599 | E88: =IFERROR('Historical FS'!$L$58/'Historical FS'!$L$5*Forecast!E33,0) -> 50346.043 | F88: =IFERROR('Historical FS'!$L$58/'Historical FS'!$L$5*Forecast!F33,0) -> 58401.41 | G88: =IFERROR('Historical FS'!$L$58/'Historical FS'!$L$5*Forecast!G33,0) -> 66577.607 | H88: =IFERROR('Historical FS'!$L$58/'Historical FS'!$L$5*Forecast!H33,0) -> 74566.92
B89: Total Non Current Assets | D89: =IFERROR(SUM(D85:D88),0) -> 56280.958 | E89: =IFERROR(SUM(E85:E88),0) -> 66761.454 | F89: =IFERROR(SUM(F85:F88),0) -> 77083.045 | G89: =IFERROR(SUM(G85:G88),0) -> 87842.738 | H89: =IFERROR(SUM(H85:H88),0) -> 98363.877
B91: Receivables | D91: =IFERROR(D33/365*D21,0) -> 3185.9777 | E91: =IFERROR(E33/365*E21,0) -> 3679.8042 | F91: =IFERROR(F33/365*F21,0) -> 4268.5729 | G91: =IFERROR(G33/365*G21,0) -> 4718.7133 | H91: =IFERROR(H33/365*H21,0) -> 5284.9589
B92: Inventory | D92: =IFERROR(D36/365*D23,0) -> 3279.6829 | E92: =IFERROR(E36/365*E23,0) -> 3757.4146 | F92: =IFERROR(F36/365*F23,0) -> 4194.843 | G92: =IFERROR(G36/365*G23,0) -> 4795.6873 | H92: =IFERROR(H36/365*H23,0) -> 5159.4411
B93: Cash & Bank | D93: =IFERROR(D83-SUM(D89,D91:D92),0) -> 4061.3462 | E93: =IFERROR(E83-SUM(E89,E91:E92),0) -> 4197.2073 | F93: =IFERROR(F83-SUM(F89,F91:F92),0) -> 4897.5812 | G93: =IFERROR(G83-SUM(G89,G91:G92),0) -> 5300.158 | H93: =IFERROR(H83-SUM(H89,H91:H92),0) -> 6010.4381
B94: Total Current Assets | D94: =IFERROR(SUM(D91:D93),0) -> 10527.007 | E94: =IFERROR(SUM(E91:E93),0) -> 11634.426 | F94: =IFERROR(SUM(F91:F93),0) -> 13360.997 | G94: =IFERROR(SUM(G91:G93),0) -> 14814.559 | H94: =IFERROR(SUM(H91:H93),0) -> 16454.838
B96: Total Assets | D96: =IFERROR(D89+D94,0) -> 66807.965 | E96: =IFERROR(E89+E94,0) -> 78395.88 | F96: =IFERROR(F89+F94,0) -> 90444.042 | G96: =IFERROR(G89+G94,0) -> 102657.3 | H96: =IFERROR(H89+H94,0) -> 114818.71
B98: Check | D98: =D83=D96 -> TRUE | E98: =E83=E96 -> TRUE | F98: =F83=F96 -> TRUE | G98: =G83=G96 -> TRUE | H98: =H83=H96 -> TRUE
A100: # | B100: Cash Flow Statements
B101: Operating Activities -
B102: Profit from operations | D102: =IFERROR(D45,0) -> 10807.961 | E102: =IFERROR(E45,0) -> 12861.473 | F102: =IFERROR(F45,0) -> 14636.031 | G102: =IFERROR(G45,0) -> 16685.075 | H102: =IFERROR(H45,0) -> 18325.595
B103: Receivables | D103: =IFERROR(-(D91-'Historical FS'!L61),0) -> -531.84766 | E103: =IFERROR(-(E91-D91),0) -> -493.82654 | F103: =IFERROR(-(F91-E91),0) -> -588.76867 | G103: =IFERROR(-(G91-F91),0) -> -450.14041 | H103: =IFERROR(-(H91-G91),0) -> -566.24559
B104: Inventory | D104: =IFERROR(-(D92-'Historical FS'!L62),0) -> -820.48288 | E104: =IFERROR(-(E92-D92),0) -> -477.73173 | F104: =IFERROR(-(F92-E92),0) -> -437.42836 | G104: =IFERROR(-(G92-F92),0) -> -600.84432 | H104: =IFERROR(-(H92-G92),0) -> -363.75381
B105: Payables | D105: =IFERROR(Forecast!D82-'Historical FS'!L52,0) -> 2889.1701 | E105: =IFERROR(E82-D82,0) -> 3169.1107 | F105: =IFERROR(F82-E82,0) -> 3434.4839 | G105: =IFERROR(G82-F82,0) -> 3259.6375 | H105: =IFERROR(H82-G82,0) -> 3185.1315
B106: Loans Advances | D106: 0 | E106: 0 | F106: 0 | G106: 0 | H106: 0
B107: Other WC items | D107: 0 | E107: 0 | F107: 0 | G107: 0 | H107: 0
B108: Working capital changes | D108: =IFERROR(SUM(D103:D107),0) -> 1536.8395 | E108: =IFERROR(SUM(E103:E107),0) -> 2197.5525 | F108: =IFERROR(SUM(F103:F107),0) -> 2408.2869 | G108: =IFERROR(SUM(G103:G107),0) -> 2208.6527 | H108: =IFERROR(SUM(H103:H107),0) -> 2255.1321
B109: Direct taxes | D109: =IFERROR(-D60,0) -> -1865.8179 | E109: =IFERROR(-E60,0) -> -2194.31 | F109: =IFERROR(-F60,0) -> -2424.2325 | G109: =IFERROR(-G60,0) -> -2707.6037 | H109: =IFERROR(-H60,0) -> -2961.7222
B110: Cash from Operating Activities | D110: =IFERROR(D102+D108+D109,0) -> 10478.982 | E110: =IFERROR(E102+E108+E109,0) -> 12864.716 | F110: =IFERROR(F102+F108+F109,0) -> 14620.085 | G110: =IFERROR(G102+G108+G109,0) -> 16186.124 | H110: =IFERROR(H102+H108+H109,0) -> 17619.005
B112: Investing Activities -
B113: Fixed assets purchased | D113: =IFERROR(-D33*D27,0) -> -3762.2648 | E113: =IFERROR(-E33*E27,0) -> -4477.0951 | F113: =IFERROR(-F33*F27,0) -> -4721.3003 | G113: =IFERROR(-G33*G27,0) -> -5382.2823 | H113: =IFERROR(-H33*H27,0) -> -5787.03
B114: Fixed assets sold | D114: 0 | E114: 0 | F114: 0 | G114: 0 | H114: 0
B115: Capital WIP | D115: 0 | E115: 0 | F115: 0 | G115: 0 | H115: 0
B116: Investments purchased | D116: 0 | E116: 0 | F116: 0 | G116: 0 | H116: 0
B117: Investments sold | D117: 0 | E117: 0 | F117: 0 | G117: 0 | H117: 0
B118: Interest received | D118: 0 | E118: 0 | F118: 0 | G118: 0 | H118: 0
B119: Dividends Received | D119: 0 | E119: 0 | F119: 0 | G119: 0 | H119: 0
B120: Investment in Group Companies | D120: 0 | E120: 0 | F120: 0 | G120: 0 | H120: 0
B121: Redemption and Cancelling of Shares | D121: 0 | E121: 0 | F121: 0 | G121: 0 | H121: 0
B122: Acquisition of companies | D122: 0 | E122: 0 | F122: 0 | G122: 0 | H122: 0
B123: Change in Other Assets | D123: =IFERROR(-(D88-'Historical FS'!L58),0) -> -7629.2392 | E123: =IFERROR(-(E88-D88),0) -> -8038.4438 | F123: =IFERROR(-(F88-E88),0) -> -8055.3669 | G123: =IFERROR(-(G88-F88),0) -> -8176.1974 | H123: =IFERROR(-(H88-G88),0) -> -7989.3129
B124: Cash from investing activities | D124: =IFERROR(SUM(D113:D123),0) -> -11391.504 | E124: =IFERROR(SUM(E113:E123),0) -> -12515.539 | F124: =IFERROR(SUM(F113:F123),0) -> -12776.667 | G124: =IFERROR(SUM(G113:G123),0) -> -13558.48 | H124: =IFERROR(SUM(H113:H123),0) -> -13776.343
B126: Financing Activity -
B127: Proceeds from shares | D127: 0 | E127: 0 | F127: 0 | G127: 0 | H127: 0
B128: Proceeds from borrowings | D128: =IFERROR(D81-'Historical FS'!L51,0) -> 3934.9212 | E128: =IFERROR(E81-D81,0) -> 3672.5931 | F128: =IFERROR(F81-E81,0) -> 3231.8819 | G128: =IFERROR(G81-F81,0) -> 2617.8244 | H128: =IFERROR(H81-G81,0) -> 2312.4115
B129: Repayment of borrowings | D129: 0
B130: Proceeds from deposits | D130: 0 | E130: 0 | F130: 0 | G130: 0 | H130: 0
B131: Interest Paid | D131: =IFERROR(-D48,0) -> -2502.6099 | E131: =IFERROR(-E48,0) -> -2699.3559 | F131: =IFERROR(-F48,0) -> -2856.9836 | G131: =IFERROR(-G48,0) -> -3055.8737 | H131: =IFERROR(-H48,0) -> -3223.5017
B132: Dividends paid | D132: =IFERROR(-D71*D66,0) -> -959.56348 | E132: =IFERROR(-E71*E66,0) -> -1186.5528 | F132: =IFERROR(-F71*F66,0) -> -1517.9425 | G132: =IFERROR(-G71*G66,0) -> -1787.0184 | H132: =IFERROR(-H71*H66,0) -> -2221.2917
B133: Financial liabilities | D133: 0 | E133: 0 | F133: 0 | G133: 0 | H133: 0
B134: Other financing items | D134: 0 | E134: 0 | F134: 0 | G134: 0 | H134: 0
B135: Cash from Financing Activities | D135: =IFERROR(SUM(D127:D134),0) -> 472.74784 | E135: =IFERROR(SUM(E127:E134),0) -> -213.31563 | F135: =IFERROR(SUM(F127:F134),0) -> -1143.0442 | G135: =IFERROR(SUM(G127:G134),0) -> -2225.0677 | H135: =IFERROR(SUM(H127:H134),0) -> -3132.3818
B137: Net Cash Flow | D137: =IFERROR(D110+D124+D135,0) -> -439.7738 | E137: =IFERROR(E110+E124+E135,0) -> 135.86108 | F137: =IFERROR(F110+F124+F135,0) -> 700.37393 | G137: =IFERROR(G110+G124+G135,0) -> 402.57683 | H137: =IFERROR(H110+H124+H135,0) -> 710.28008
